Workbook

Sheet Assumptions
A1: LUMINA — ALL ASSUMPTIONS (Researched April 2026)
A3: FX RATES
A4: EUR/CHF | B4: 0.9224 | C4: 1 EUR = 0.9224 CHF. Multiply. ECB Apr 3 2026
A5: USD/CHF | B5: 0.8 | C5: 1 USD = 0.80 CHF. Multiply. Apr 4 2026
A6: €1,000 → CHF | B6: 922
A7: $600 → CHF | B7: 480
A9: CAPITAL
A10: Initial capital (CHF) | B10: 200000 | C10: Swiss AG share capital, hard CHF
A12: ARPU (EUR/hotel/month)
B13: Phase 1 M1-23 | C13: Phase 2 M24-36 | D13: Phase 3 M37-48
A14: Chain | B14: 1000 | C14: 1400 | D14: 1800
A15: Indie | B15: 1000 | C15: 1500 | D15: 2000
A17: CHAIN SCHEDULE (10 chains, 48 months)
A18: Kempinski: M1, 82 hotels total
A19: Radisson: M12, 95 hotels total
A20: Barceló: M16, 70 hotels total
A21: Mandarin Oriental: M20, 36 hotels total
A22: Hyatt Luxury: M24, 45 hotels total
A23: Jumeirah: M28, 26 hotels total
A24: Meliá: M32, 80 hotels total
A25: Rosewood: M36, 30 hotels total
A26: Minor Hotels: M40, 55 hotels total
A27: Rotana: M44, 42 hotels total
A28: Trial: 3 hotels free for 3 months. Rollout pays immediately.
... A33: CEO SALARY (CHF, researched social contributions)
A34: CHF 106,080 → company cost CHF 9,737/mo | B34: 9737 | C34: 10.14% employer social
A35: CHF 150,000 → company cost CHF 13,689/mo | B35: 13689 | C35: 9.51%
A36: CHF 185,000 → company cost CHF 16,817/mo | B36: 16817 | C36: 9.09%
A37: CHF 220,000 → company cost CHF 19,945/mo | B37: 19945 | C37: 8.79%
A38: Step-ups: €300K→150K, €1.5M→185K, €3M→220K + runway clause
A40: TEAM (EUR/mo total company cost per person)
A41: Developer FT: €4,000 = CHF 3,690/mo from M1
A42: PM PT: €4,000 = CHF 3,690/mo from M1
A43: CS: €5,000 = CHF 4,612/mo from M12
A44: Senior Eng: €7,000 = CHF 6,457/mo from M18
A45: Sales/BD: €6,000 = CHF 5,534/mo from M18
A46: Engineer: €6,000 = CHF 5,534/mo from M30
A47: Marketing: €5,000 = CHF 4,612/mo from M36
A49: DEV TOOLING ($600 USD = CHF 480)
A50: Claude Code Max 20x | B50: 160 | C50: $200
A51: OpenAI Codex Pro | B51: 160 | C51: $200
A52: Perplexity Max | B52: 160 | C52: $200
A54: INFRASTRUCTURE (each SaaS tool, USD → CHF)
A55: Supabase Pro+compute | B55: $75→CHF 60 | C55: $110→CHF 88 | D55: $150→CHF 120 | E55: $200→CHF 160
A56: Vercel Pro+usage | B56: $150→CHF 120 | C56: $200→CHF 160 | D56: $300→CHF 240 | E56: $400→CHF 320
A57: DataForSEO | B57: $75→CHF 60 | C57: $150→CHF 120 | D57: $200→CHF 160 | E57: $250→CHF 200
A58: SerpApi | B58: $75→CHF 60 | C58: $75→CHF 60 | D58: $150→CHF 120 | E58: $150→CHF 120
A59: Firecrawl Standard | B59: $47→CHF 38 | C59: $47→CHF 38 | D59: $47→CHF 38 | E59: $47→CHF 38
A60: Google Workspace | B60: $35→CHF 28 | C60: $50→CHF 40 | D60: $70→CHF 56 | E60: $70→CHF 56
A61: Domain renewal | B61: $7→CHF 6 | C61: $7→CHF 6 | D61: $7→CHF 6 | E61: $7→CHF 6
A62: 1Password | B62: $24→CHF 19 | C62: $40→CHF 32 | D62: $56→CHF 45 | E62: $64→CHF 51
A63: Canva Pro | B63: $13→CHF 10 | C63: $13→CHF 10 | D63: $13→CHF 10 | E63: $13→CHF 10
A64: Sentry Team | B64: $26→CHF 21 | C64: $26→CHF 21 | D64: $26→CHF 21 | E64: $26→CHF 21
A65: Resend Pro | B65: $20→CHF 16 | C65: $20→CHF 16 | D65: $20→CHF 16 | E65: $20→CHF 16
A66: Notion Plus | B66: $20→CHF 16 | C66: $30→CHF 24 | D66: $30→CHF 24 | E66: $30→CHF 24
... A72: Misc+overages | B72: $25→CHF 20 | C72: $30→CHF 24 | D72: $40→CHF 32 | E72: $50→CHF 40
A74: ADMIN (CHF native)
A75: Treuhand | B75: 300 | C75: 300 | D75: 500 | E75: 700
A76: Legal | B76: 250 | C76: 250 | D76: 300 | E76: 400
A77: D&O ins. | B77: 167 | C77: 167 | D77: 200 | E77: 250
A78: Cyber ins. | B78: 34 | C78: 34 | D78: 50 | E78: 75
A79: Liability | B79: 100 | C79: 100 | D79: 100 | E79: 100
A80: Banking | B80: 30 | C80: 30 | D80: 50 | E80: 50
A82: WORKSPACE (CHF)
A83: Internet: CHF 40/mo (Sunrise 1Gbit)
A84: Coworking: M1-12 CHF 0, M13 CHF 350, M25 CHF 500, M37 CHF 700
A86: ONE-TIME COSTS (CHF, M1)
A87: Nexova AG Plus formation | B87: 690
A88: Commercial register | B88: 650
A89: Notary Zug | B89: 1000
A90: Capital deposit account | B90: 250
A91: Signature certs ×5 | B91: 100
A92: MacBook Pro 16" M5 Pro 64GB/2TB | B92: 3700
A93: Apple Studio Display 2026 | B93: 1290
A94: Logitech MX Keys S keyboard | B94: 83
A95: Logitech MX Master 3S mouse | B95: 69
A96: Ergotron LX monitor arm | B96: 165
A97: Legal (SHA, PSOP, contracts) | B97: 4000
A98: Domain .ai (2yr) | B98: 128
A99: TOTAL ONE-TIME | B99: 12125
A101: EQUITY
A102: Amedeo 40% / Corsaro 40% / Marco 20% base / PSOP 5% off cap
A103: EXIT KICKER
A104: Under €30M: 20% | €30M+: 23% | €50M+: 25% | €100M+ (cap): 30%
A105: VESTING
A106: M12: +5% (15+ paying) | M24: +7% (ARR≥€500K) | M36: +8% (ARR≥€1.5M)
A107: ANTI-DILUTION
A108: 10% floor through Series A, 8% from Series B. Pro-rata.
A110: ZUG vs ZURICH
A111: Baar/Zug profit tax: 11.82% | C111: Saves CHF 38K-78K/yr vs Zurich at 19.59%
A112: Zurich City profit tax: 19.59% | C112: +7.77pp higher
A113: Zurich notary: +CHF 500 | C113: CHF 1,500 vs CHF 1,000
A114: FAK Zurich: 0.98% vs Zug 1.35% | C114: CHF 400/yr cheaper per employee

Sheet Monthly P&L
A1: LUMINA — MONTHLY P&L (CHF) — ZUG/BAAR
B3: Y1 | C3: Y1 | D3: Y1 | E3: Y1 | F3: Y1 | G3: Y1 | H3: Y1 | I3: Y1 | J3: Y1 | K3: Y1 | L3: Y1 | M3: Y1 | N3: Y2 | O3: Y2 | P3: Y2 | Q3: Y2 | R3: Y2 | S3: Y2 | T3: Y2 | U3: Y2 | V3: Y2 | W3: Y2 | X3: Y2 | Y3: Y2 | Z3: Y3 | AA3: Y3 | AB3: Y3 | AC3: Y3 | AD3: Y3 | AE3: Y3 | AF3: Y3 | AG3: Y3 | AH3: Y3 | AI3: Y3 | AJ3: Y3 | AK3: Y3 | AL3: Y4 | AM3: Y4 | AN3: Y4 | AO3: Y4 | AP3: Y4 | AQ3: Y4 | AR3: Y4 | AS3: Y4 | AT3: Y4 | AU3: Y4 | AV3: Y4 | AW3: Y4 | AX3: Y1 | AY3: Y2 | AZ3: Y3 | BA3: Y4
A4: Month | B4: M1 | C4: M2 | D4: M3 | E4: M4 | F4: M5 | G4: M6 | H4: M7 | I4: M8 | J4: M9 | K4: M10 | L4: M11 | M4: M12 | N4: M13 | O4: M14 | P4: M15 | Q4: M16 | R4: M17 | S4: M18 | T4: M19 | U4: M20 | V4: M21 | W4: M22 | X4: M23 | Y4: M24 | Z4: M25 | AA4: M26 | AB4: M27 | AC4: M28 | AD4: M29 | AE4: M30 | AF4: M31 | AG4: M32 | AH4: M33 | AI4: M34 | AJ4: M35 | AK4: M36 | AL4: M37 | AM4: M38 | AN4: M39 | AO4: M40 | AP4: M41 | AQ4: M42 | AR4: M43 | AS4: M44 | AT4: M45 | AU4: M46 | AV4: M47 | AW4: M48
A5: HOTEL COUNTS
A6: Kempinski | B6: 3 | C6: 3 | D6: 3 | E6: 3 | F6: 3 | G6: 12 | H6: 12 | I6: 12 | J6: 12 | K6: 12 | L6: 12 | M6: 33 | N6: 33 | O6: 33 | P6: 33 | Q6: 33 | R6: 33 | S6: 41 | T6: 41 | U6: 41 | V6: 41 | W6: 41 | X6: 41 | Y6: 45 | Z6: 45 | AA6: 45 | AB6: 45 | AC6: 45 | AD6: 45 | AE6: 45 | AF6: 45 | AG6: 45 | AH6: 45 | AI6: 45 | AJ6: 45 | AK6: 45 | AL6: 45 | AM6: 45 | AN6: 45 | AO6: 45 | AP6: 45 | AQ6: 45 | AR6: 45 | AS6: 45 | AT6: 45 | AU6: 45 | AV6: 45 | AW6: 45 | AX6: 33 | AY6: 45 | AZ6: 45 | BA6: 45
A7: Radisson | B7: 0 | C7: 0 | D7: 0 | E7: 0 | F7: 0 | G7: 0 | H7: 0 | I7: 0 | J7: 0 | K7: 0 | L7: 0 | M7: 3 | N7: 3 | O7: 3 | P7: 3 | Q7: 3 | R7: 14 | S7: 14 | T7: 14 | U7: 14 | V7: 14 | W7: 14 | X7: 38 | Y7: 38 | Z7: 38 | AA7: 38 | AB7: 38 | AC7: 38 | AD7: 48 | AE7: 48 | AF7: 48 | AG7: 48 | AH7: 48 | AI7: 48 | AJ7: 52 | AK7: 52 | AL7: 52 | AM7: 52 | AN7: 52 | AO7: 52 | AP7: 52 | AQ7: 52 | AR7: 52 | AS7: 52 | AT7: 52 | AU7: 52 | AV7: 52 | AW7: 52 | AX7: 3 | AY7: 38 | AZ7: 52 | BA7: 52
A8: Barceló | B8: 0 | C8: 0 | D8: 0 | E8: 0 | F8: 0 | G8: 0 | H8: 0 | I8: 0 | J8: 0 | K8: 0 | L8: 0 | M8: 0 | N8: 0 | O8: 0 | P8: 0 | Q8: 3 | R8: 3 | S8: 3 | T8: 3 | U8: 3 | V8: 10 | W8: 10 | X8: 10 | Y8: 10 | Z8: 10 | AA8: 10 | AB8: 28 | AC8: 28 | AD8: 28 | AE8: 28 | AF8: 28 | AG8: 28 | AH8: 35 | AI8: 35 | AJ8: 35 | AK8: 35 | AL8: 35 | AM8: 35 | AN8: 38 | AO8: 38 | AP8: 38 | AQ8: 38 | AR8: 38 | AS8: 38 | AT8: 38 | AU8: 38 | AV8: 38 | AW8: 38 | AX8: 0 | AY8: 10 | AZ8: 35 | BA8: 38
A9: Mandarin Oriental | B9: 0 | C9: 0 | D9: 0 | E9: 0 | F9: 0 | G9: 0 | H9: 0 | I9: 0 | J9: 0 | K9: 0 | L9: 0 | M9: 0 | N9: 0 | O9: 0 | P9: 0 | Q9: 0 | R9: 0 | S9: 0 | T9: 0 | U9: 3 | V9: 3 | W9: 3 | X9: 3 | Y9: 3 | Z9: 5 | AA9: 5 | AB9: 5 | AC9: 5 | AD9: 5 | AE9: 5 | AF9: 14 | AG9: 14 | AH9: 14 | AI9: 14 | AJ9: 14 | AK9: 14 | AL9: 18 | AM9: 18 | AN9: 18 | AO9: 18 | AP9: 18 | AQ9: 18 | AR9: 20 | AS9: 20 | AT9: 20 | AU9: 20 | AV9: 20 | AW9: 20 | AX9: 0 | AY9: 3 | AZ9: 14 | BA9: 20
A10: Hyatt Luxury | B10: 0 | C10: 0 | D10: 0 | E10: 0 | F10: 0 | G10: 0 | H10: 0 | I10: 0 | J10: 0 | K10: 0 | L10: 0 | M10: 0 | N10: 0 | O10: 0 | P10: 0 | Q10: 0 | R10: 0 | S10: 0 | T10: 0 | U10: 0 | V10: 0 | W10: 0 | X10: 0 | Y10: 3 | Z10: 3 | AA10: 3 | AB10: 3 | AC10: 3 | AD10: 7 | AE10: 7 | AF10: 7 | AG10: 7 | AH10: 7 | AI10: 7 | AJ10: 18 | AK10: 18 | AL10: 18 | AM10: 18 | AN10: 18 | AO10: 18 | AP10: 22 | AQ10: 22 | AR10: 22 | AS10: 22 | AT10: 22 | AU10: 22 | AV10: 25 | AW10: 25 | AX10: 0 | AY10: 3 | AZ10: 18 | BA10: 25
A11: Jumeirah | B11: 0 | C11: 0 | D11: 0 | E11: 0 | F11: 0 | G11: 0 | H11: 0 | I11: 0 | J11: 0 | K11: 0 | L11: 0 | M11: 0 | N11: 0 | O11: 0 | P11: 0 | Q11: 0 | R11: 0 | S11: 0 | T11: 0 | U11: 0 | V11: 0 | W11: 0 | X11: 0 | Y11: 0 | Z11: 0 | AA11: 0 | AB11: 0 | AC11: 3 | AD11: 3 | AE11: 3 | AF11: 3 | AG11: 3 | AH11: 4 | AI11: 4 | AJ11: 4 | AK11: 4 | AL11: 4 | AM11: 4 | AN11: 10 | AO11: 10 | AP11: 10 | AQ11: 10 | AR11: 10 | AS11: 10 | AT11: 13 | AU11: 13 | AV11: 13 | AW11: 13 | AX11: 0 | AY11: 0 | AZ11: 4 | BA11: 13
A12: Meliá | B12: 0 | C12: 0 | D12: 0 | E12: 0 | F12: 0 | G12: 0 | H12: 0 | I12: 0 | J12: 0 | K12: 0 | L12: 0 | M12: 0 | N12: 0 | O12: 0 | P12: 0 | Q12: 0 | R12: 0 | S12: 0 | T12: 0 | U12: 0 | V12: 0 | W12: 0 | X12: 0 | Y12: 0 | Z12: 0 | AA12: 0 | AB12: 0 | AC12: 0 | AD12: 0 | AE12: 0 | AF12: 0 | AG12: 3 | AH12: 3 | AI12: 3 | AJ12: 3 | AK12: 3 | AL12: 12 | AM12: 12 | AN12: 12 | AO12: 12 | AP12: 12 | AQ12: 12 | AR12: 32 | AS12: 32 | AT12: 32 | AU12: 32 | AV12: 32 | AW12: 32 | AX12: 0 | AY12: 0 | AZ12: 3 | BA12: 32
A13: Rosewood | B13: 0 | C13: 0 | D13: 0 | E13: 0 | F13: 0 | G13: 0 | H13: 0 | I13: 0 | J13: 0 | K13: 0 | L13: 0 | M13: 0 | N13: 0 | O13: 0 | P13: 0 | Q13: 0 | R13: 0 | S13: 0 | T13: 0 | U13: 0 | V13: 0 | W13: 0 | X13: 0 | Y13: 0 | Z13: 0 | AA13: 0 | AB13: 0 | AC13: 0 | AD13: 0 | AE13: 0 | AF13: 0 | AG13: 0 | AH13: 0 | AI13: 0 | AJ13: 0 | AK13: 3 | AL13: 3 | AM13: 3 | AN13: 3 | AO13: 3 | AP13: 4 | AQ13: 4 | AR13: 4 | AS13: 4 | AT13: 4 | AU13: 4 | AV13: 12 | AW13: 12 | AX13: 0 | AY13: 0 | AZ13: 3 | BA13: 12
A14: Minor Hotels | B14: 0 | C14: 0 | D14: 0 | E14: 0 | F14: 0 | G14: 0 | H14: 0 | I14: 0 | J14: 0 | K14: 0 | L14: 0 | M14: 0 | N14: 0 | O14: 0 | P14: 0 | Q14: 0 | R14: 0 | S14: 0 | T14: 0 | U14: 0 | V14: 0 | W14: 0 | X14: 0 | Y14: 0 | Z14: 0 | AA14: 0 | AB14: 0 | AC14: 0 | AD14: 0 | AE14: 0 | AF14: 0 | AG14: 0 | AH14: 0 | AI14: 0 | AJ14: 0 | AK14: 0 | AL14: 0 | AM14: 0 | AN14: 0 | AO14: 3 | AP14: 3 | AQ14: 3 | AR14: 3 | AS14: 3 | AT14: 8 | AU14: 8 | AV14: 8 | AW14: 8 | AX14: 0 | AY14: 0 | AZ14: 0 | BA14: 8
A15: Rotana | B15: 0 | C15: 0 | D15: 0 | E15: 0 | F15: 0 | G15: 0 | H15: 0 | I15: 0 | J15: 0 | K15: 0 | L15: 0 | M15: 0 | N15: 0 | O15: 0 | P15: 0 | Q15: 0 | R15: 0 | S15: 0 | T15: 0 | U15: 0 | V15: 0 | W15: 0 | X15: 0 | Y15: 0 | Z15: 0 | AA15: 0 | AB15: 0 | AC15: 0 | AD15: 0 | AE15: 0 | AF15: 0 | AG15: 0 | AH15: 0 | AI15: 0 | AJ15: 0 | AK15: 0 | AL15: 0 | AM15: 0 | AN15: 0 | AO15: 0 | AP15: 0 | AQ15: 0 | AR15: 0 | AS15: 3 | AT15: 3 | AU15: 3 | AV15: 3 | AW15: 3 | AX15: 0 | AY15: 0 | AZ15: 0 | BA15: 3
A16: Total chain active | B16: 3 | C16: 3 | D16: 3 | E16: 3 | F16: 3 | G16: 12 | H16: 12 | I16: 12 | J16: 12 | K16: 12 | L16: 12 | M16: 36 | N16: 36 | O16: 36 | P16: 36 | Q16: 39 | R16: 50 | S16: 58 | T16: 58 | U16: 61 | V16: 68 | W16: 68 | X16: 92 | Y16: 99 | Z16: 101 | AA16: 101 | AB16: 119 | AC16: 122 | AD16: 136 | AE16: 136 | AF16: 145 | AG16: 148 | AH16: 156 | AI16: 156 | AJ16: 171 | AK16: 174 | AL16: 187 | AM16: 187 | AN16: 196 | AO16: 199 | AP16: 204 | AQ16: 204 | AR16: 226 | AS16: 229 | AT16: 237 | AU16: 237 | AV16: 248 | AW16: 248 | AX16: 36 | AY16: 99 | AZ16: 174 | BA16: 248
A17: Independent active | B17: 0 | C17: 0 | D17: 0 | E17: 0 | F17: 0 | G17: 0 | H17: 2 | I17: 4 | J17: 6 | K17: 8 | L17: 10 | M17: 12 | N17: 14 | O17: 16 | P17: 18 | Q17: 20 | R17: 22 | S17: 24 | T17: 26 | U17: 28 | V17: 30 | W17: 32 | X17: 34 | Y17: 36 | Z17: 38 | AA17: 40 | AB17: 42 | AC17: 44 | AD17: 46 | AE17: 48 | AF17: 51 | AG17: 53 | AH17: 55 | AI17: 57 | AJ17: 59 | AK17: 61 | AL17: 63 | AM17: 65 | AN17: 67 | AO17: 69 | AP17: 71 | AQ17: 73 | AR17: 75 | AS17: 77 | AT17: 79 | AU17: 81 | AV17: 83 | AW17: 85 | AX17: 12 | AY17: 36 | AZ17: 61 | BA17: 85
... A21: TOTAL PAYING | B21: 0 | C21: 0 | D21: 0 | E21: 3 | F21: 3 | G21: 12 | H21: 14 | I21: 16 | J21: 18 | K21: 20 | L21: 22 | M21: 45 | N21: 47 | O21: 49 | P21: 54 | Q21: 56 | R21: 69 | S21: 79 | T21: 84 | U21: 86 | V21: 95 | W21: 97 | X21: 126 | Y21: 132 | Z21: 136 | AA21: 138 | AB21: 161 | AC21: 163 | AD21: 179 | AE21: 181 | AF21: 196 | AG21: 198 | AH21: 208 | AI21: 210 | AJ21: 230 | AK21: 232 | AL21: 247 | AM21: 249 | AN21: 263 | AO21: 265 | AP21: 272 | AQ21: 274 | AR21: 301 | AS21: 303 | AT21: 313 | AU21: 315 | AV21: 331 | AW21: 333 | AX21: 45 | AY21: 132 | AZ21: 232 | BA21: 333
A23: REVENUE (CHF)
A24: Chain revenue | B24: 0 | C24: 0 | D24: 0 | E24: 2767 | F24: 2767 | G24: 11069 | H24: 11069 | I24: 11069 | J24: 11069 | K24: 11069 | L24: 11069 | M24: 30439 | N24: 30439 | O24: 30439 | P24: 33206 | Q24: 33206 | R24: 43353 | S24: 50732 | T24: 53499 | U24: 53499 | V24: 59956 | W24: 59956 | X24: 84861 | Y24: 123971 | Z24: 126553 | AA24: 126553 | AB24: 153672 | AC24: 153672 | AD24: 171751 | AE24: 171751 | AF24: 187247 | AG24: 187247 | AH24: 197578 | AI24: 197578 | AJ24: 220823 | AK24: 220823 | AL24: 305499 | AM24: 305499 | AN24: 325423 | AO24: 325423 | AP24: 333724 | AQ24: 333724 | AR24: 375232 | AS24: 375232 | AT24: 388515 | AU24: 388515 | AV24: 411759 | AW24: 411759 | AX24: 102387 | AY24: 657117 | AZ24: 2115248 | BA24: 4280304
A25: Indie revenue | B25: 0 | C25: 0 | D25: 0 | E25: 0 | F25: 0 | G25: 0 | H25: 1845 | I25: 3690 | J25: 5534 | K25: 7379 | L25: 9224 | M25: 11069 | N25: 12914 | O25: 14758 | P25: 16603 | Q25: 18448 | R25: 20293 | S25: 22138 | T25: 23982 | U25: 25827 | V25: 27672 | W25: 29517 | X25: 31362 | Y25: 49810 | Z25: 52577 | AA25: 55344 | AB25: 58111 | AC25: 60878 | AD25: 63646 | AE25: 66413 | AF25: 70564 | AG25: 73331 | AH25: 76098 | AI25: 78865 | AJ25: 81632 | AK25: 84400 | AL25: 116222 | AM25: 119912 | AN25: 123602 | AO25: 127291 | AP25: 130981 | AQ25: 134670 | AR25: 138360 | AS25: 142050 | AT25: 145739 | AU25: 149429 | AV25: 153118 | AW25: 156808 | AX25: 38741 | AY25: 293324 | AZ25: 821859 | BA25: 1638182
A26: TOTAL REVENUE | B26: 0 | C26: 0 | D26: 0 | E26: 2767 | F26: 2767 | G26: 11069 | H26: 12914 | I26: 14759 | J26: 16603 | K26: 18448 | L26: 20293 | M26: 41508 | N26: 43353 | O26: 45197 | P26: 49809 | Q26: 51654 | R26: 63646 | S26: 72870 | T26: 77481 | U26: 79326 | V26: 87628 | W26: 89473 | X26: 116223 | Y26: 173781 | Z26: 179130 | AA26: 181897 | AB26: 211783 | AC26: 214550 | AD26: 235397 | AE26: 238164 | AF26: 257811 | AG26: 260578 | AH26: 273676 | AI26: 276443 | AJ26: 302455 | AK26: 305223 | AL26: 421721 | AM26: 425411 | AN26: 449025 | AO26: 452714 | AP26: 464705 | AQ26: 468394 | AR26: 513592 | AS26: 517282 | AT26: 534254 | AU26: 537944 | AV26: 564877 | AW26: 568567 | AX26: 141128 | AY26: 950441 | AZ26: 2937107 | BA26: 5918486
A27: ARR (CHF) | B27: =B26*12 | C27: =C26*12 | D27: =D26*12 | E27: =E26*12 | F27: =F26*12 | G27: =G26*12 | H27: =H26*12 | I27: =I26*12 | ... AW27: =AW26*12 | AX27: =M27 | AY27: =Y27 | AZ27: =AK27 | BA27: =AW27
A28: ARR (EUR) | B28: =B27/0.9224 | C28: =C27/0.9224 | D28: =D27/0.9224 | E28: =E27/0.9224 | F28: =F27/0.9224 | G28: =G27/0.9224 | H28: =H27/0.9224 | I28: =I27/0.9224 | ... AW28: =AW27/0.9224 | AX28: =M28 | AY28: =Y28 | AZ28: =AK28 | BA28: =AW28
A30: COSTS (CHF) — EVERY ITEM
A31: — People
A32: CEO gross salary (CHF) | B32: 8840 | C32: 8840 | D32: 8840 | E32: 8840 | F32: 8840 | G32: 8840 | H32: 8840 | I32: 8840 | J32: 8840 | K32: 8840 | L32: 8840 | M32: 12500 | N32: 12500 | O32: 12500 | P32: 12500 | Q32: 12500 | R32: 12500 | S32: 12500 | T32: 12500 | U32: 12500 | V32: 12500 | W32: 12500 | X32: 15417 | Y32: 15417 | Z32: 15417 | AA32: 15417 | AB32: 15417 | AC32: 15417 | AD32: 18333 | AE32: 18333 | AF32: 18333 | AG32: 18333 | AH32: 18333 | AI32: 18333 | AJ32: 18333 | AK32: 18333 | AL32: 18333 | AM32: 18333 | AN32: 18333 | AO32: 18333 | AP32: 18333 | AQ32: 18333 | AR32: 18333 | AS32: 18333 | AT32: 18333 | AU32: 18333 | AV32: 18333 | AW32: 18333 | AX32: 109740 | AY32: 155834 | AZ32: 208332 | BA32: 219996
A33: CEO employer social (10.1%) | B33: 897 | C33: 897 | D33: 897 | E33: 897 | F33: 897 | G33: 897 | H33: 897 | I33: 897 | J33: 897 | K33: 897 | L33: 897 | M33: 1189 | N33: 1189 | O33: 1189 | P33: 1189 | Q33: 1189 | R33: 1189 | S33: 1189 | T33: 1189 | U33: 1189 | V33: 1189 | W33: 1189 | X33: 1400 | Y33: 1400 | Z33: 1400 | AA33: 1400 | AB33: 1400 | AC33: 1400 | AD33: 1612 | AE33: 1612 | AF33: 1612 | AG33: 1612 | AH33: 1612 | AI33: 1612 | AJ33: 1612 | AK33: 1612 | AL33: 1612 | AM33: 1612 | AN33: 1612 | AO33: 1612 | AP33: 1612 | AQ33: 1612 | AR33: 1612 | AS33: 1612 | AT33: 1612 | AU33: 1612 | AV33: 1612 | AW33: 1612 | AX33: 11056 | AY33: 14690 | AZ33: 18496 | BA33: 19344
A34: Developer FT (€4K/mo) | B34: 3690 | C34: 3690 | D34: 3690 | E34: 3690 | F34: 3690 | G34: 3690 | H34: 3690 | I34: 3690 | J34: 3690 | K34: 3690 | L34: 3690 | M34: 3690 | N34: 3690 | O34: 3690 | P34: 3690 | Q34: 3690 | R34: 3690 | S34: 3690 | T34: 3690 | U34: 3690 | V34: 3690 | W34: 3690 | X34: 3690 | Y34: 3690 | Z34: 3690 | AA34: 3690 | AB34: 3690 | AC34: 3690 | AD34: 3690 | AE34: 3690 | AF34: 3690 | AG34: 3690 | AH34: 3690 | AI34: 3690 | AJ34: 3690 | AK34: 3690 | AL34: 3690 | AM34: 3690 | AN34: 3690 | AO34: 3690 | AP34: 3690 | AQ34: 3690 | AR34: 3690 | AS34: 3690 | AT34: 3690 | AU34: 3690 | AV34: 3690 | AW34: 3690 | AX34: 44280 | AY34: 44280 | AZ34: 44280 | BA34: 44280
A35: PM PT (€4K/mo) | B35: 3690 | C35: 3690 | D35: 3690 | E35: 3690 | F35: 3690 | G35: 3690 | H35: 3690 | I35: 3690 | J35: 3690 | K35: 3690 | L35: 3690 | M35: 3690 | N35: 3690 | O35: 3690 | P35: 3690 | Q35: 3690 | R35: 3690 | S35: 3690 | T35: 3690 | U35: 3690 | V35: 3690 | W35: 3690 | X35: 3690 | Y35: 3690 | Z35: 3690 | AA35: 3690 | AB35: 3690 | AC35: 3690 | AD35: 3690 | AE35: 3690 | AF35: 3690 | AG35: 3690 | AH35: 3690 | AI35: 3690 | AJ35: 3690 | AK35: 3690 | AL35: 3690 | AM35: 3690 | AN35: 3690 | AO35: 3690 | AP35: 3690 | AQ35: 3690 | AR35: 3690 | AS35: 3690 | AT35: 3690 | AU35: 3690 | AV35: 3690 | AW35: 3690 | AX35: 44280 | AY35: 44280 | AZ35: 44280 | BA35: 44280
A36: CS/Implementation (€5K/mo, M12+) | B36: 0 | C36: 0 | D36: 0 | E36: 0 | F36: 0 | G36: 0 | H36: 0 | I36: 0 | J36: 0 | K36: 0 | L36: 0 | M36: 4612 | N36: 4612 | O36: 4612 | P36: 4612 | Q36: 4612 | R36: 4612 | S36: 4612 | T36: 4612 | U36: 4612 | V36: 4612 | W36: 4612 | X36: 4612 | Y36: 4612 | Z36: 4612 | AA36: 4612 | AB36: 4612 | AC36: 4612 | AD36: 4612 | AE36: 4612 | AF36: 4612 | AG36: 4612 | AH36: 4612 | AI36: 4612 | AJ36: 4612 | AK36: 4612 | AL36: 4612 | AM36: 4612 | AN36: 4612 | AO36: 4612 | AP36: 4612 | AQ36: 4612 | AR36: 4612 | AS36: 4612 | AT36: 4612 | AU36: 4612 | AV36: 4612 | AW36: 4612 | AX36: 4612 | AY36: 55344 | AZ36: 55344 | BA36: 55344
A37: Senior Engineer (€7K/mo, M18+) | B37: 0 | C37: 0 | D37: 0 | E37: 0 | F37: 0 | G37: 0 | H37: 0 | I37: 0 | J37: 0 | K37: 0 | L37: 0 | M37: 0 | N37: 0 | O37: 0 | P37: 0 | Q37: 0 | R37: 0 | S37: 6457 | T37: 6457 | U37: 6457 | V37: 6457 | W37: 6457 | X37: 6457 | Y37: 6457 | Z37: 6457 | AA37: 6457 | AB37: 6457 | AC37: 6457 | AD37: 6457 | AE37: 6457 | AF37: 6457 | AG37: 6457 | AH37: 6457 | AI37: 6457 | AJ37: 6457 | AK37: 6457 | AL37: 6457 | AM37: 6457 | AN37: 6457 | AO37: 6457 | AP37: 6457 | AQ37: 6457 | AR37: 6457 | AS37: 6457 | AT37: 6457 | AU37: 6457 | AV37: 6457 | AW37: 6457 | AX37: 0 | AY37: 45199 | AZ37: 77484 | BA37: 77484
A38: Sales/BD (€6K/mo, M18+) | B38: 0 | C38: 0 | D38: 0 | E38: 0 | F38: 0 | G38: 0 | H38: 0 | I38: 0 | J38: 0 | K38: 0 | L38: 0 | M38: 0 | N38: 0 | O38: 0 | P38: 0 | Q38: 0 | R38: 0 | S38: 5534 | T38: 5534 | U38: 5534 | V38: 5534 | W38: 5534 | X38: 5534 | Y38: 5534 | Z38: 5534 | AA38: 5534 | AB38: 5534 | AC38: 5534 | AD38: 5534 | AE38: 5534 | AF38: 5534 | AG38: 5534 | AH38: 5534 | AI38: 5534 | AJ38: 5534 | AK38: 5534 | AL38: 5534 | AM38: 5534 | AN38: 5534 | AO38: 5534 | AP38: 5534 | AQ38: 5534 | AR38: 5534 | AS38: 5534 | AT38: 5534 | AU38: 5534 | AV38: 5534 | AW38: 5534 | AX38: 0 | AY38: 38738 | AZ38: 66408 | BA38: 66408
A39: Engineer (€6K/mo, M30+) | B39: 0 | C39: 0 | D39: 0 | E39: 0 | F39: 0 | G39: 0 | H39: 0 | I39: 0 | J39: 0 | K39: 0 | L39: 0 | M39: 0 | N39: 0 | O39: 0 | P39: 0 | Q39: 0 | R39: 0 | S39: 0 | T39: 0 | U39: 0 | V39: 0 | W39: 0 | X39: 0 | Y39: 0 | Z39: 0 | AA39: 0 | AB39: 0 | AC39: 0 | AD39: 0 | AE39: 5534 | AF39: 5534 | AG39: 5534 | AH39: 5534 | AI39: 5534 | AJ39: 5534 | AK39: 5534 | AL39: 5534 | AM39: 5534 | AN39: 5534 | AO39: 5534 | AP39: 5534 | AQ39: 5534 | AR39: 5534 | AS39: 5534 | AT39: 5534 | AU39: 5534 | AV39: 5534 | AW39: 5534 | AX39: 0 | AY39: 0 | AZ39: 38738 | BA39: 66408
A40: Marketing (€5K/mo, M36+) | B40: 0 | C40: 0 | D40: 0 | E40: 0 | F40: 0 | G40: 0 | H40: 0 | I40: 0 | J40: 0 | K40: 0 | L40: 0 | M40: 0 | N40: 0 | O40: 0 | P40: 0 | Q40: 0 | R40: 0 | S40: 0 | T40: 0 | U40: 0 | V40: 0 | W40: 0 | X40: 0 | Y40: 0 | Z40: 0 | AA40: 0 | AB40: 0 | AC40: 0 | AD40: 0 | AE40: 0 | AF40: 0 | AG40: 0 | AH40: 0 | AI40: 0 | AJ40: 0 | AK40: 4612 | AL40: 4612 | AM40: 4612 | AN40: 4612 | AO40: 4612 | AP40: 4612 | AQ40: 4612 | AR40: 4612 | AS40: 4612 | AT40: 4612 | AU40: 4612 | AV40: 4612 | AW40: 4612 | AX40: 0 | AY40: 0 | AZ40: 4612 | BA40: 55344
A41: — AI & Technology
A42: AI COGS (€50/hotel/mo) | B42: 0 | C42: 0 | D42: 0 | E42: 138 | F42: 138 | G42: 553 | H42: 646 | I42: 738 | J42: 830 | K42: 922 | L42: 1015 | M42: 2075 | N42: 2168 | O42: 2260 | P42: 2490 | Q42: 2583 | R42: 3182 | S42: 3643 | T42: 3874 | U42: 3966 | V42: 4381 | W42: 4474 | X42: 5811 | Y42: 6088 | Z42: 6272 | AA42: 6365 | AB42: 7425 | AC42: 7518 | AD42: 8255 | AE42: 8348 | AF42: 9040 | AG42: 9132 | AH42: 9593 | AI42: 9685 | AJ42: 10608 | AK42: 10700 | AL42: 11392 | AM42: 11484 | AN42: 12130 | AO42: 12222 | AP42: 12545 | AQ42: 12637 | AR42: 13882 | AS42: 13974 | AT42: 14436 | AU42: 14528 | AV42: 15266 | AW42: 15358 | AX42: 7055 | AY42: 44920 | AZ42: 102941 | BA42: 159854
A43: Claude Code Max 20x ($200) | B43: 160 | C43: 160 | D43: 160 | E43: 160 | F43: 160 | G43: 160 | H43: 160 | I43: 160 | J43: 160 | K43: 160 | L43: 160 | M43: 160 | N43: 160 | O43: 160 | P43: 160 | Q43: 160 | R43: 160 | S43: 160 | T43: 160 | U43: 160 | V43: 160 | W43: 160 | X43: 160 | Y43: 160 | Z43: 160 | AA43: 160 | AB43: 160 | AC43: 160 | AD43: 160 | AE43: 160 | AF43: 160 | AG43: 160 | AH43: 160 | AI43: 160 | AJ43: 160 | AK43: 160 | AL43: 160 | AM43: 160 | AN43: 160 | AO43: 160 | AP43: 160 | AQ43: 160 | AR43: 160 | AS43: 160 | AT43: 160 | AU43: 160 | AV43: 160 | AW43: 160 | AX43: 1920 | AY43: 1920 | AZ43: 1920 | BA43: 1920
A44: OpenAI Codex Pro ($200) | B44: 160 | C44: 160 | D44: 160 | E44: 160 | F44: 160 | G44: 160 | H44: 160 | I44: 160 | J44: 160 | K44: 160 | L44: 160 | M44: 160 | N44: 160 | O44: 160 | P44: 160 | Q44: 160 | R44: 160 | S44: 160 | T44: 160 | U44: 160 | V44: 160 | W44: 160 | X44: 160 | Y44: 160 | Z44: 160 | AA44: 160 | AB44: 160 | AC44: 160 | AD44: 160 | AE44: 160 | AF44: 160 | AG44: 160 | AH44: 160 | AI44: 160 | AJ44: 160 | AK44: 160 | AL44: 160 | AM44: 160 | AN44: 160 | AO44: 160 | AP44: 160 | AQ44: 160 | AR44: 160 | AS44: 160 | AT44: 160 | AU44: 160 | AV44: 160 | AW44: 160 | AX44: 1920 | AY44: 1920 | AZ44: 1920 | BA44: 1920
A45: Perplexity Max ($200) | B45: 160 | C45: 160 | D45: 160 | E45: 160 | F45: 160 | G45: 160 | H45: 160 | I45: 160 | J45: 160 | K45: 160 | L45: 160 | M45: 160 | N45: 160 | O45: 160 | P45: 160 | Q45: 160 | R45: 160 | S45: 160 | T45: 160 | U45: 160 | V45: 160 | W45: 160 | X45: 160 | Y45: 160 | Z45: 160 | AA45: 160 | AB45: 160 | AC45: 160 | AD45: 160 | AE45: 160 | AF45: 160 | AG45: 160 | AH45: 160 | AI45: 160 | AJ45: 160 | AK45: 160 | AL45: 160 | AM45: 160 | AN45: 160 | AO45: 160 | AP45: 160 | AQ45: 160 | AR45: 160 | AS45: 160 | AT45: 160 | AU45: 160 | AV45: 160 | AW45: 160 | AX45: 1920 | AY45: 1920 | AZ45: 1920 | BA45: 1920
A46: — Infrastructure (SaaS)
A47: Supabase Pro + compute | B47: 60 | C47: 60 | D47: 60 | E47: 60 | F47: 60 | G47: 60 | H47: 60 | I47: 60 | J47: 60 | K47: 60 | L47: 60 | M47: 60 | N47: 88 | O47: 88 | P47: 88 | Q47: 88 | R47: 88 | S47: 88 | T47: 88 | U47: 88 | V47: 88 | W47: 88 | X47: 88 | Y47: 88 | Z47: 120 | AA47: 120 | AB47: 120 | AC47: 120 | AD47: 120 | AE47: 120 | AF47: 120 | AG47: 120 | AH47: 120 | AI47: 120 | AJ47: 120 | AK47: 120 | AL47: 160 | AM47: 160 | AN47: 160 | AO47: 160 | AP47: 160 | AQ47: 160 | AR47: 160 | AS47: 160 | AT47: 160 | AU47: 160 | AV47: 160 | AW47: 160 | AX47: 720 | AY47: 1056 | AZ47: 1440 | BA47: 1920
A48: Vercel Pro | B48: 120 | C48: 120 | D48: 120 | E48: 120 | F48: 120 | G48: 120 | H48: 120 | I48: 120 | J48: 120 | K48: 120 | L48: 120 | M48: 120 | N48: 160 | O48: 160 | P48: 160 | Q48: 160 | R48: 160 | S48: 160 | T48: 160 | U48: 160 | V48: 160 | W48: 160 | X48: 160 | Y48: 160 | Z48: 240 | AA48: 240 | AB48: 240 | AC48: 240 | AD48: 240 | AE48: 240 | AF48: 240 | AG48: 240 | AH48: 240 | AI48: 240 | AJ48: 240 | AK48: 240 | AL48: 320 | AM48: 320 | AN48: 320 | AO48: 320 | AP48: 320 | AQ48: 320 | AR48: 320 | AS48: 320 | AT48: 320 | AU48: 320 | AV48: 320 | AW48: 320 | AX48: 1440 | AY48: 1920 | AZ48: 2880 | BA48: 3840
A49: DataForSEO usage | B49: 60 | C49: 60 | D49: 60 | E49: 60 | F49: 60 | G49: 60 | H49: 60 | I49: 60 | J49: 60 | K49: 60 | L49: 60 | M49: 60 | N49: 120 | O49: 120 | P49: 120 | Q49: 120 | R49: 120 | S49: 120 | T49: 120 | U49: 120 | V49: 120 | W49: 120 | X49: 120 | Y49: 120 | Z49: 160 | AA49: 160 | AB49: 160 | AC49: 160 | AD49: 160 | AE49: 160 | AF49: 160 | AG49: 160 | AH49: 160 | AI49: 160 | AJ49: 160 | AK49: 160 | AL49: 200 | AM49: 200 | AN49: 200 | AO49: 200 | AP49: 200 | AQ49: 200 | AR49: 200 | AS49: 200 | AT49: 200 | AU49: 200 | AV49: 200 | AW49: 200 | AX49: 720 | AY49: 1440 | AZ49: 1920 | BA49: 2400
A50: SerpApi Developer | B50: 60 | C50: 60 | D50: 60 | E50: 60 | F50: 60 | G50: 60 | H50: 60 | I50: 60 | J50: 60 | K50: 60 | L50: 60 | M50: 60 | N50: 60 | O50: 60 | P50: 60 | Q50: 60 | R50: 60 | S50: 60 | T50: 60 | U50: 60 | V50: 60 | W50: 60 | X50: 60 | Y50: 60 | Z50: 120 | AA50: 120 | AB50: 120 | AC50: 120 | AD50: 120 | AE50: 120 | AF50: 120 | AG50: 120 | AH50: 120 | AI50: 120 | AJ50: 120 | AK50: 120 | AL50: 120 | AM50: 120 | AN50: 120 | AO50: 120 | AP50: 120 | AQ50: 120 | AR50: 120 | AS50: 120 | AT50: 120 | AU50: 120 | AV50: 120 | AW50: 120 | AX50: 720 | AY50: 720 | AZ50: 1440 | BA50: 1440
A51: Firecrawl | B51: 38 | C51: 38 | D51: 38 | E51: 38 | F51: 38 | G51: 38 | H51: 38 | I51: 38 | J51: 38 | K51: 38 | L51: 38 | M51: 38 | N51: 38 | O51: 38 | P51: 38 | Q51: 38 | R51: 38 | S51: 38 | T51: 38 | U51: 38 | V51: 38 | W51: 38 | X51: 38 | Y51: 38 | Z51: 38 | AA51: 38 | AB51: 38 | AC51: 38 | AD51: 38 | AE51: 38 | AF51: 38 | AG51: 38 | AH51: 38 | AI51: 38 | AJ51: 38 | AK51: 38 | AL51: 38 | AM51: 38 | AN51: 38 | AO51: 38 | AP51: 38 | AQ51: 38 | AR51: 38 | AS51: 38 | AT51: 38 | AU51: 38 | AV51: 38 | AW51: 38 | AX51: 456 | AY51: 456 | AZ51: 456 | BA51: 456
A52: Google Workspace | B52: 28 | C52: 28 | D52: 28 | E52: 28 | F52: 28 | G52: 28 | H52: 28 | I52: 28 | J52: 28 | K52: 28 | L52: 28 | M52: 28 | N52: 40 | O52: 40 | P52: 40 | Q52: 40 | R52: 40 | S52: 40 | T52: 40 | U52: 40 | V52: 40 | W52: 40 | X52: 40 | Y52: 40 | Z52: 56 | AA52: 56 | AB52: 56 | AC52: 56 | AD52: 56 | AE52: 56 | AF52: 56 | AG52: 56 | AH52: 56 | AI52: 56 | AJ52: 56 | AK52: 56 | AL52: 56 | AM52: 56 | AN52: 56 | AO52: 56 | AP52: 56 | AQ52: 56 | AR52: 56 | AS52: 56 | AT52: 56 | AU52: 56 | AV52: 56 | AW52: 56 | AX52: 336 | AY52: 480 | AZ52: 672 | BA52: 672
A53: Domain .ai renewal | B53: 6 | C53: 6 | D53: 6 | E53: 6 | F53: 6 | G53: 6 | H53: 6 | I53: 6 | J53: 6 | K53: 6 | L53: 6 | M53: 6 | N53: 6 | O53: 6 | P53: 6 | Q53: 6 | R53: 6 | S53: 6 | T53: 6 | U53: 6 | V53: 6 | W53: 6 | X53: 6 | Y53: 6 | Z53: 6 | AA53: 6 | AB53: 6 | AC53: 6 | AD53: 6 | AE53: 6 | AF53: 6 | AG53: 6 | AH53: 6 | AI53: 6 | AJ53: 6 | AK53: 6 | AL53: 6 | AM53: 6 | AN53: 6 | AO53: 6 | AP53: 6 | AQ53: 6 | AR53: 6 | AS53: 6 | AT53: 6 | AU53: 6 | AV53: 6 | AW53: 6 | AX53: 72 | AY53: 72 | AZ53: 72 | BA53: 72
A54: 1Password Business | B54: 19 | C54: 19 | D54: 19 | E54: 19 | F54: 19 | G54: 19 | H54: 19 | I54: 19 | J54: 19 | K54: 19 | L54: 19 | M54: 19 | N54: 32 | O54: 32 | P54: 32 | Q54: 32 | R54: 32 | S54: 32 | T54: 32 | U54: 32 | V54: 32 | W54: 32 | X54: 32 | Y54: 32 | Z54: 45 | AA54: 45 | AB54: 45 | AC54: 45 | AD54: 45 | AE54: 45 | AF54: 45 | AG54: 45 | AH54: 45 | AI54: 45 | AJ54: 45 | AK54: 45 | AL54: 51 | AM54: 51 | AN54: 51 | AO54: 51 | AP54: 51 | AQ54: 51 | AR54: 51 | AS54: 51 | AT54: 51 | AU54: 51 | AV54: 51 | AW54: 51 | AX54: 228 | AY54: 384 | AZ54: 540 | BA54: 612
A55: Canva Pro | B55: 10 | C55: 10 | D55: 10 | E55: 10 | F55: 10 | G55: 10 | H55: 10 | I55: 10 | J55: 10 | K55: 10 | L55: 10 | M55: 10 | N55: 10 | O55: 10 | P55: 10 | Q55: 10 | R55: 10 | S55: 10 | T55: 10 | U55: 10 | V55: 10 | W55: 10 | X55: 10 | Y55: 10 | Z55: 10 | AA55: 10 | AB55: 10 | AC55: 10 | AD55: 10 | AE55: 10 | AF55: 10 | AG55: 10 | AH55: 10 | AI55: 10 | AJ55: 10 | AK55: 10 | AL55: 10 | AM55: 10 | AN55: 10 | AO55: 10 | AP55: 10 | AQ55: 10 | AR55: 10 | AS55: 10 | AT55: 10 | AU55: 10 | AV55: 10 | AW55: 10 | AX55: 120 | AY55: 120 | AZ55: 120 | BA55: 120
A56: Sentry monitoring | B56: 21 | C56: 21 | D56: 21 | E56: 21 | F56: 21 | G56: 21 | H56: 21 | I56: 21 | J56: 21 | K56: 21 | L56: 21 | M56: 21 | N56: 21 | O56: 21 | P56: 21 | Q56: 21 | R56: 21 | S56: 21 | T56: 21 | U56: 21 | V56: 21 | W56: 21 | X56: 21 | Y56: 21 | Z56: 21 | AA56: 21 | AB56: 21 | AC56: 21 | AD56: 21 | AE56: 21 | AF56: 21 | AG56: 21 | AH56: 21 | AI56: 21 | AJ56: 21 | AK56: 21 | AL56: 21 | AM56: 21 | AN56: 21 | AO56: 21 | AP56: 21 | AQ56: 21 | AR56: 21 | AS56: 21 | AT56: 21 | AU56: 21 | AV56: 21 | AW56: 21 | AX56: 252 | AY56: 252 | AZ56: 252 | BA56: 252
A57: Resend email | B57: 16 | C57: 16 | D57: 16 | E57: 16 | F57: 16 | G57: 16 | H57: 16 | I57: 16 | J57: 16 | K57: 16 | L57: 16 | M57: 16 | N57: 16 | O57: 16 | P57: 16 | Q57: 16 | R57: 16 | S57: 16 | T57: 16 | U57: 16 | V57: 16 | W57: 16 | X57: 16 | Y57: 16 | Z57: 16 | AA57: 16 | AB57: 16 | AC57: 16 | AD57: 16 | AE57: 16 | AF57: 16 | AG57: 16 | AH57: 16 | AI57: 16 | AJ57: 16 | AK57: 16 | AL57: 16 | AM57: 16 | AN57: 16 | AO57: 16 | AP57: 16 | AQ57: 16 | AR57: 16 | AS57: 16 | AT57: 16 | AU57: 16 | AV57: 16 | AW57: 16 | AX57: 192 | AY57: 192 | AZ57: 192 | BA57: 192
A58: Notion | B58: 16 | C58: 16 | D58: 16 | E58: 16 | F58: 16 | G58: 16 | H58: 16 | I58: 16 | J58: 16 | K58: 16 | L58: 16 | M58: 16 | N58: 24 | O58: 24 | P58: 24 | Q58: 24 | R58: 24 | S58: 24 | T58: 24 | U58: 24 | V58: 24 | W58: 24 | X58: 24 | Y58: 24 | Z58: 24 | AA58: 24 | AB58: 24 | AC58: 24 | AD58: 24 | AE58: 24 | AF58: 24 | AG58: 24 | AH58: 24 | AI58: 24 | AJ58: 24 | AK58: 24 | AL58: 24 | AM58: 24 | AN58: 24 | AO58: 24 | AP58: 24 | AQ58: 24 | AR58: 24 | AS58: 24 | AT58: 24 | AU58: 24 | AV58: 24 | AW58: 24 | AX58: 192 | AY58: 288 | AZ58: 288 | BA58: 288
A59: Cloudflare Pro | B59: 16 | C59: 16 | D59: 16 | E59: 16 | F59: 16 | G59: 16 | H59: 16 | I59: 16 | J59: 16 | K59: 16 | L59: 16 | M59: 16 | N59: 16 | O59: 16 | P59: 16 | Q59: 16 | R59: 16 | S59: 16 | T59: 16 | U59: 16 | V59: 16 | W59: 16 | X59: 16 | Y59: 16 | Z59: 16 | AA59: 16 | AB59: 16 | AC59: 16 | AD59: 16 | AE59: 16 | AF59: 16 | AG59: 16 | AH59: 16 | AI59: 16 | AJ59: 16 | AK59: 16 | AL59: 16 | AM59: 16 | AN59: 16 | AO59: 16 | AP59: 16 | AQ59: 16 | AR59: 16 | AS59: 16 | AT59: 16 | AU59: 16 | AV59: 16 | AW59: 16 | AX59: 192 | AY59: 192 | AZ59: 192 | BA59: 192
A60: — Admin & Professional
A61: Slack Pro | B61: 20 | C61: 20 | D61: 20 | E61: 20 | F61: 20 | G61: 20 | H61: 20 | I61: 20 | J61: 20 | K61: 20 | L61: 20 | M61: 20 | N61: 32 | O61: 32 | P61: 32 | Q61: 32 | R61: 32 | S61: 32 | T61: 32 | U61: 32 | V61: 32 | W61: 32 | X61: 32 | Y61: 32 | Z61: 45 | AA61: 45 | AB61: 45 | AC61: 45 | AD61: 45 | AE61: 45 | AF61: 45 | AG61: 45 | AH61: 45 | AI61: 45 | AJ61: 45 | AK61: 45 | AL61: 51 | AM61: 51 | AN61: 51 | AO61: 51 | AP61: 51 | AQ61: 51 | AR61: 51 | AS61: 51 | AT61: 51 | AU61: 51 | AV61: 51 | AW61: 51 | AX61: 240 | AY61: 384 | AZ61: 540 | BA61: 612
A62: GitHub Actions (CI/CD) | B62: 12 | C62: 12 | D62: 12 | E62: 12 | F62: 12 | G62: 12 | H62: 12 | I62: 12 | J62: 12 | K62: 12 | L62: 12 | M62: 12 | N62: 16 | O62: 16 | P62: 16 | Q62: 16 | R62: 16 | S62: 16 | T62: 16 | U62: 16 | V62: 16 | W62: 16 | X62: 16 | Y62: 16 | Z62: 24 | AA62: 24 | AB62: 24 | AC62: 24 | AD62: 24 | AE62: 24 | AF62: 24 | AG62: 24 | AH62: 24 | AI62: 24 | AJ62: 24 | AK62: 24 | AL62: 32 | AM62: 32 | AN62: 32 | AO62: 32 | AP62: 32 | AQ62: 32 | AR62: 32 | AS62: 32 | AT62: 32 | AU62: 32 | AV62: 32 | AW62: 32 | AX62: 144 | AY62: 192 | AZ62: 288 | BA62: 384
A63: Upstash Redis (caching) | B63: 8 | C63: 8 | D63: 8 | E63: 8 | F63: 8 | G63: 8 | H63: 8 | I63: 8 | J63: 8 | K63: 8 | L63: 8 | M63: 8 | N63: 16 | O63: 16 | P63: 16 | Q63: 16 | R63: 16 | S63: 16 | T63: 16 | U63: 16 | V63: 16 | W63: 16 | X63: 16 | Y63: 16 | Z63: 24 | AA63: 24 | AB63: 24 | AC63: 24 | AD63: 24 | AE63: 24 | AF63: 24 | AG63: 24 | AH63: 24 | AI63: 24 | AJ63: 24 | AK63: 24 | AL63: 24 | AM63: 24 | AN63: 24 | AO63: 24 | AP63: 24 | AQ63: 24 | AR63: 24 | AS63: 24 | AT63: 24 | AU63: 24 | AV63: 24 | AW63: 24 | AX63: 96 | AY63: 192 | AZ63: 288 | BA63: 288
A64: PostHog analytics | B64: 0 | C64: 0 | D64: 0 | E64: 0 | F64: 0 | G64: 0 | H64: 0 | I64: 0 | J64: 0 | K64: 0 | L64: 0 | M64: 0 | N64: 20 | O64: 20 | P64: 20 | Q64: 20 | R64: 20 | S64: 20 | T64: 20 | U64: 20 | V64: 20 | W64: 20 | X64: 20 | Y64: 20 | Z64: 40 | AA64: 40 | AB64: 40 | AC64: 40 | AD64: 40 | AE64: 40 | AF64: 40 | AG64: 40 | AH64: 40 | AI64: 40 | AJ64: 40 | AK64: 40 | AL64: 40 | AM64: 40 | AN64: 40 | AO64: 40 | AP64: 40 | AQ64: 40 | AR64: 40 | AS64: 40 | AT64: 40 | AU64: 40 | AV64: 40 | AW64: 40 | AX64: 0 | AY64: 240 | AZ64: 480 | BA64: 480
A65: Misc SaaS + overages | B65: 20 | C65: 20 | D65: 20 | E65: 20 | F65: 20 | G65: 20 | H65: 20 | I65: 20 | J65: 20 | K65: 20 | L65: 20 | M65: 20 | N65: 24 | O65: 24 | P65: 24 | Q65: 24 | R65: 24 | S65: 24 | T65: 24 | U65: 24 | V65: 24 | W65: 24 | X65: 24 | Y65: 24 | Z65: 32 | AA65: 32 | AB65: 32 | AC65: 32 | AD65: 32 | AE65: 32 | AF65: 32 | AG65: 32 | AH65: 32 | AI65: 32 | AJ65: 32 | AK65: 32 | AL65: 40 | AM65: 40 | AN65: 40 | AO65: 40 | AP65: 40 | AQ65: 40 | AR65: 40 | AS65: 40 | AT65: 40 | AU65: 40 | AV65: 40 | AW65: 40 | AX65: 240 | AY65: 288 | AZ65: 384 | BA65: 480
A66: Treuhand / accounting | B66: 300 | C66: 300 | D66: 300 | E66: 300 | F66: 300 | G66: 300 | H66: 300 | I66: 300 | J66: 300 | K66: 300 | L66: 300 | M66: 300 | N66: 300 | O66: 300 | P66: 300 | Q66: 300 | R66: 300 | S66: 300 | T66: 300 | U66: 300 | V66: 300 | W66: 300 | X66: 300 | Y66: 300 | Z66: 500 | AA66: 500 | AB66: 500 | AC66: 500 | AD66: 500 | AE66: 500 | AF66: 500 | AG66: 500 | AH66: 500 | AI66: 500 | AJ66: 500 | AK66: 500 | AL66: 700 | AM66: 700 | AN66: 700 | AO66: 700 | AP66: 700 | AQ66: 700 | AR66: 700 | AS66: 700 | AT66: 700 | AU66: 700 | AV66: 700 | AW66: 700 | AX66: 3600 | AY66: 3600 | AZ66: 6000 | BA66: 8400
A67: — Workspace
A68: Legal retainer | B68: 250 | C68: 250 | D68: 250 | E68: 250 | F68: 250 | G68: 250 | H68: 250 | I68: 250 | J68: 250 | K68: 250 | L68: 250 | M68: 250 | N68: 250 | O68: 250 | P68: 250 | Q68: 250 | R68: 250 | S68: 250 | T68: 250 | U68: 250 | V68: 250 | W68: 250 | X68: 250 | Y68: 250 | Z68: 300 | AA68: 300 | AB68: 300 | AC68: 300 | AD68: 300 | AE68: 300 | AF68: 300 | AG68: 300 | AH68: 300 | AI68: 300 | AJ68: 300 | AK68: 300 | AL68: 400 | AM68: 400 | AN68: 400 | AO68: 400 | AP68: 400 | AQ68: 400 | AR68: 400 | AS68: 400 | AT68: 400 | AU68: 400 | AV68: 400 | AW68: 400 | AX68: 3000 | AY68: 3000 | AZ68: 3600 | BA68: 4800
A69: D&O insurance (CHF 1M cover) | B69: 167 | C69: 167 | D69: 167 | E69: 167 | F69: 167 | G69: 167 | H69: 167 | I69: 167 | J69: 167 | K69: 167 | L69: 167 | M69: 167 | N69: 167 | O69: 167 | P69: 167 | Q69: 167 | R69: 167 | S69: 167 | T69: 167 | U69: 167 | V69: 167 | W69: 167 | X69: 167 | Y69: 167 | Z69: 200 | AA69: 200 | AB69: 200 | AC69: 200 | AD69: 200 | AE69: 200 | AF69: 200 | AG69: 200 | AH69: 200 | AI69: 200 | AJ69: 200 | AK69: 200 | AL69: 250 | AM69: 250 | AN69: 250 | AO69: 250 | AP69: 250 | AQ69: 250 | AR69: 250 | AS69: 250 | AT69: 250 | AU69: 250 | AV69: 250 | AW69: 250 | AX69: 2004 | AY69: 2004 | AZ69: 2400 | BA69: 3000
A70: — Sales & Marketing
A71: Cyber insurance | B71: 34 | C71: 34 | D71: 34 | E71: 34 | F71: 34 | G71: 34 | H71: 34 | I71: 34 | J71: 34 | K71: 34 | L71: 34 | M71: 34 | N71: 34 | O71: 34 | P71: 34 | Q71: 34 | R71: 34 | S71: 34 | T71: 34 | U71: 34 | V71: 34 | W71: 34 | X71: 34 | Y71: 34 | Z71: 50 | AA71: 50 | AB71: 50 | AC71: 50 | AD71: 50 | AE71: 50 | AF71: 50 | AG71: 50 | AH71: 50 | AI71: 50 | AJ71: 50 | AK71: 50 | AL71: 75 | AM71: 75 | AN71: 75 | AO71: 75 | AP71: 75 | AQ71: 75 | AR71: 75 | AS71: 75 | AT71: 75 | AU71: 75 | AV71: 75 | AW71: 75 | AX71: 408 | AY71: 408 | AZ71: 600 | BA71: 900
A72: General liability insurance | B72: 100 | C72: 100 | D72: 100 | E72: 100 | F72: 100 | G72: 100 | H72: 100 | I72: 100 | J72: 100 | K72: 100 | L72: 100 | M72: 100 | N72: 100 | O72: 100 | P72: 100 | Q72: 100 | R72: 100 | S72: 100 | T72: 100 | U72: 100 | V72: 100 | W72: 100 | X72: 100 | Y72: 100 | Z72: 100 | AA72: 100 | AB72: 100 | AC72: 100 | AD72: 100 | AE72: 100 | AF72: 100 | AG72: 100 | AH72: 100 | AI72: 100 | AJ72: 100 | AK72: 100 | AL72: 100 | AM72: 100 | AN72: 100 | AO72: 100 | AP72: 100 | AQ72: 100 | AR72: 100 | AS72: 100 | AT72: 100 | AU72: 100 | AV72: 100 | AW72: 100 | AX72: 1200 | AY72: 1200 | AZ72: 1200 | BA72: 1200
A73: — Variable & Other
A74: Banking + FX (UBS/Wise) | B74: 30 | C74: 30 | D74: 30 | E74: 30 | F74: 30 | G74: 30 | H74: 30 | I74: 30 | J74: 30 | K74: 30 | L74: 30 | M74: 30 | N74: 30 | O74: 30 | P74: 30 | Q74: 30 | R74: 30 | S74: 30 | T74: 30 | U74: 30 | V74: 30 | W74: 30 | X74: 30 | Y74: 30 | Z74: 50 | AA74: 50 | AB74: 50 | AC74: 50 | AD74: 50 | AE74: 50 | AF74: 50 | AG74: 50 | AH74: 50 | AI74: 50 | AJ74: 50 | AK74: 50 | AL74: 50 | AM74: 50 | AN74: 50 | AO74: 50 | AP74: 50 | AQ74: 50 | AR74: 50 | AS74: 50 | AT74: 50 | AU74: 50 | AV74: 50 | AW74: 50 | AX74: 360 | AY74: 360 | AZ74: 600 | BA74: 600
A75: Internet (Sunrise 1Gbit) | B75: 40 | C75: 40 | D75: 40 | E75: 40 | F75: 40 | G75: 40 | H75: 40 | I75: 40 | J75: 40 | K75: 40 | L75: 40 | M75: 40 | N75: 40 | O75: 40 | P75: 40 | Q75: 40 | R75: 40 | S75: 40 | T75: 40 | U75: 40 | V75: 40 | W75: 40 | X75: 40 | Y75: 40 | Z75: 40 | AA75: 40 | AB75: 40 | AC75: 40 | AD75: 40 | AE75: 40 | AF75: 40 | AG75: 40 | AH75: 40 | AI75: 40 | AJ75: 40 | AK75: 40 | AL75: 40 | AM75: 40 | AN75: 40 | AO75: 40 | AP75: 40 | AQ75: 40 | AR75: 40 | AS75: 40 | AT75: 40 | AU75: 40 | AV75: 40 | AW75: 40 | AX75: 480 | AY75: 480 | AZ75: 480 | BA75: 480
A76: — One-Time (M1 only)
A77: Coworking (Westhive Zug) | B77: 0 | C77: 0 | D77: 0 | E77: 0 | F77: 0 | G77: 0 | H77: 0 | I77: 0 | J77: 0 | K77: 0 | L77: 0 | M77: 0 | N77: 350 | O77: 350 | P77: 350 | Q77: 350 | R77: 350 | S77: 350 | T77: 350 | U77: 350 | V77: 350 | W77: 350 | X77: 350 | Y77: 350 | Z77: 500 | AA77: 500 | AB77: 500 | AC77: 500 | AD77: 500 | AE77: 500 | AF77: 500 | AG77: 500 | AH77: 500 | AI77: 500 | AJ77: 500 | AK77: 500 | AL77: 700 | AM77: 700 | AN77: 700 | AO77: 700 | AP77: 700 | AQ77: 700 | AR77: 700 | AS77: 700 | AT77: 700 | AU77: 700 | AV77: 700 | AW77: 700 | AX77: 0 | AY77: 4200 | AZ77: 6000 | BA77: 8400
A78: Travel (client visits) | B78: 400 | C78: 400 | D78: 400 | E78: 400 | F78: 400 | G78: 400 | H78: 400 | I78: 400 | J78: 400 | K78: 400 | L78: 400 | M78: 400 | N78: 1000 | O78: 1000 | P78: 1000 | Q78: 1000 | R78: 1000 | S78: 1000 | T78: 1000 | U78: 1000 | V78: 1000 | W78: 1000 | X78: 1000 | Y78: 1000 | Z78: 1500 | AA78: 1500 | AB78: 1500 | AC78: 1500 | AD78: 1500 | AE78: 1500 | AF78: 1500 | AG78: 1500 | AH78: 1500 | AI78: 1500 | AJ78: 1500 | AK78: 1500 | AL78: 2000 | AM78: 2000 | AN78: 2000 | AO78: 2000 | AP78: 2000 | AQ78: 2000 | AR78: 2000 | AS78: 2000 | AT78: 2000 | AU78: 2000 | AV78: 2000 | AW78: 2000 | AX78: 4800 | AY78: 12000 | AZ78: 18000 | BA78: 24000
A79: Marketing & events | B79: 500 | C79: 500 | D79: 500 | E79: 500 | F79: 500 | G79: 500 | H79: 500 | I79: 500 | J79: 500 | K79: 500 | L79: 500 | M79: 500 | N79: 1500 | O79: 1500 | P79: 1500 | Q79: 1500 | R79: 1500 | S79: 1500 | T79: 1500 | U79: 1500 | V79: 1500 | W79: 1500 | X79: 1500 | Y79: 1500 | Z79: 2500 | AA79: 2500 | AB79: 2500 | AC79: 2500 | AD79: 2500 | AE79: 2500 | AF79: 2500 | AG79: 2500 | AH79: 2500 | AI79: 2500 | AJ79: 2500 | AK79: 2500 | AL79: 3500 | AM79: 3500 | AN79: 3500 | AO79: 3500 | AP79: 3500 | AQ79: 3500 | AR79: 3500 | AS79: 3500 | AT79: 3500 | AU79: 3500 | AV79: 3500 | AW79: 3500 | AX79: 6000 | AY79: 18000 | AZ79: 30000 | BA79: 42000
A80: Payment processing (Stripe 3%) | B80: 0 | C80: 0 | D80: 0 | E80: 83 | F80: 83 | G80: 332 | H80: 387 | I80: 443 | J80: 498 | K80: 553 | L80: 609 | M80: 1245 | N80: 1301 | O80: 1356 | P80: 1494 | Q80: 1550 | R80: 1909 | S80: 2186 | T80: 2324 | U80: 2380 | V80: 2629 | W80: 2684 | X80: 3487 | Y80: 5213 | Z80: 5374 | AA80: 5457 | AB80: 6353 | AC80: 6436 | AD80: 7062 | AE80: 7145 | AF80: 7734 | AG80: 7817 | AH80: 8210 | AI80: 8293 | AJ80: 9074 | AK80: 9157 | AL80: 12652 | AM80: 12762 | AN80: 13471 | AO80: 13581 | AP80: 13941 | AQ80: 14052 | AR80: 15408 | AS80: 15518 | AT80: 16028 | AU80: 16138 | AV80: 16946 | AW80: 17057 | AX80: 4233 | AY80: 28513 | AZ80: 88112 | BA80: 177554
A81: Contingency buffer | B81: 300 | C81: 300 | D81: 300 | E81: 300 | F81: 300 | G81: 300 | H81: 300 | I81: 300 | J81: 300 | K81: 300 | L81: 300 | M81: 300 | N81: 300 | O81: 300 | P81: 300 | Q81: 300 | R81: 300 | S81: 300 | T81: 300 | U81: 300 | V81: 300 | W81: 300 | X81: 300 | Y81: 300 | Z81: 300 | AA81: 300 | AB81: 300 | AC81: 300 | AD81: 300 | AE81: 300 | AF81: 300 | AG81: 300 | AH81: 300 | AI81: 300 | AJ81: 300 | AK81: 300 | AL81: 300 | AM81: 300 | AN81: 300 | AO81: 300 | AP81: 300 | AQ81: 300 | AR81: 300 | AS81: 300 | AT81: 300 | AU81: 300 | AV81: 300 | AW81: 300 | AX81: 3600 | AY81: 3600 | AZ81: 3600 | BA81: 3600
A82: One-time: Nexova AG Plus formation | B82: 690 | C82: 0 | D82: 0 | E82: 0 | F82: 0 | G82: 0 | H82: 0 | I82: 0 | J82: 0 | K82: 0 | L82: 0 | M82: 0 | N82: 0 | O82: 0 | P82: 0 | Q82: 0 | R82: 0 | S82: 0 | T82: 0 | U82: 0 | V82: 0 | W82: 0 | X82: 0 | Y82: 0 | Z82: 0 | AA82: 0 | AB82: 0 | AC82: 0 | AD82: 0 | AE82: 0 | AF82: 0 | AG82: 0 | AH82: 0 | AI82: 0 | AJ82: 0 | AK82: 0 | AL82: 0 | AM82: 0 | AN82: 0 | AO82: 0 | AP82: 0 | AQ82: 0 | AR82: 0 | AS82: 0 | AT82: 0 | AU82: 0 | AV82: 0 | AW82: 0 | AX82: 690 | AY82: 0 | AZ82: 0 | BA82: 0
A83: One-time: Commercial register entry | B83: 650 | C83: 0 | D83: 0 | E83: 0 | F83: 0 | G83: 0 | H83: 0 | I83: 0 | J83: 0 | K83: 0 | L83: 0 | M83: 0 | N83: 0 | O83: 0 | P83: 0 | Q83: 0 | R83: 0 | S83: 0 | T83: 0 | U83: 0 | V83: 0 | W83: 0 | X83: 0 | Y83: 0 | Z83: 0 | AA83: 0 | AB83: 0 | AC83: 0 | AD83: 0 | AE83: 0 | AF83: 0 | AG83: 0 | AH83: 0 | AI83: 0 | AJ83: 0 | AK83: 0 | AL83: 0 | AM83: 0 | AN83: 0 | AO83: 0 | AP83: 0 | AQ83: 0 | AR83: 0 | AS83: 0 | AT83: 0 | AU83: 0 | AV83: 0 | AW83: 0 | AX83: 650 | AY83: 0 | AZ83: 0 | BA83: 0
A84: One-time: Notary fee (Zug tariff) | B84: 1000 | C84: 0 | D84: 0 | E84: 0 | F84: 0 | G84: 0 | H84: 0 | I84: 0 | J84: 0 | K84: 0 | L84: 0 | M84: 0 | N84: 0 | O84: 0 | P84: 0 | Q84: 0 | R84: 0 | S84: 0 | T84: 0 | U84: 0 | V84: 0 | W84: 0 | X84: 0 | Y84: 0 | Z84: 0 | AA84: 0 | AB84: 0 | AC84: 0 | AD84: 0 | AE84: 0 | AF84: 0 | AG84: 0 | AH84: 0 | AI84: 0 | AJ84: 0 | AK84: 0 | AL84: 0 | AM84: 0 | AN84: 0 | AO84: 0 | AP84: 0 | AQ84: 0 | AR84: 0 | AS84: 0 | AT84: 0 | AU84: 0 | AV84: 0 | AW84: 0 | AX84: 1000 | AY84: 0 | AZ84: 0 | BA84: 0
A85: One-time: Capital deposit account | B85: 250 | C85: 0 | D85: 0 | E85: 0 | F85: 0 | G85: 0 | H85: 0 | I85: 0 | J85: 0 | K85: 0 | L85: 0 | M85: 0 | N85: 0 | O85: 0 | P85: 0 | Q85: 0 | R85: 0 | S85: 0 | T85: 0 | U85: 0 | V85: 0 | W85: 0 | X85: 0 | Y85: 0 | Z85: 0 | AA85: 0 | AB85: 0 | AC85: 0 | AD85: 0 | AE85: 0 | AF85: 0 | AG85: 0 | AH85: 0 | AI85: 0 | AJ85: 0 | AK85: 0 | AL85: 0 | AM85: 0 | AN85: 0 | AO85: 0 | AP85: 0 | AQ85: 0 | AR85: 0 | AS85: 0 | AT85: 0 | AU85: 0 | AV85: 0 | AW85: 0 | AX85: 250 | AY85: 0 | AZ85: 0 | BA85: 0
A86: One-time: Signature certifications | B86: 100 | C86: 0 | D86: 0 | E86: 0 | F86: 0 | G86: 0 | H86: 0 | I86: 0 | J86: 0 | K86: 0 | L86: 0 | M86: 0 | N86: 0 | O86: 0 | P86: 0 | Q86: 0 | R86: 0 | S86: 0 | T86: 0 | U86: 0 | V86: 0 | W86: 0 | X86: 0 | Y86: 0 | Z86: 0 | AA86: 0 | AB86: 0 | AC86: 0 | AD86: 0 | AE86: 0 | AF86: 0 | AG86: 0 | AH86: 0 | AI86: 0 | AJ86: 0 | AK86: 0 | AL86: 0 | AM86: 0 | AN86: 0 | AO86: 0 | AP86: 0 | AQ86: 0 | AR86: 0 | AS86: 0 | AT86: 0 | AU86: 0 | AV86: 0 | AW86: 0 | AX86: 100 | AY86: 0 | AZ86: 0 | BA86: 0
A87: One-time: MacBook Pro 16" M5 Pro 64GB/2TB | B87: 3700 | C87: 0 | D87: 0 | E87: 0 | F87: 0 | G87: 0 | H87: 0 | I87: 0 | J87: 0 | K87: 0 | L87: 0 | M87: 0 | N87: 0 | O87: 0 | P87: 0 | Q87: 0 | R87: 0 | S87: 0 | T87: 0 | U87: 0 | V87: 0 | W87: 0 | X87: 0 | Y87: 0 | Z87: 0 | AA87: 0 | AB87: 0 | AC87: 0 | AD87: 0 | AE87: 0 | AF87: 0 | AG87: 0 | AH87: 0 | AI87: 0 | AJ87: 0 | AK87: 0 | AL87: 0 | AM87: 0 | AN87: 0 | AO87: 0 | AP87: 0 | AQ87: 0 | AR87: 0 | AS87: 0 | AT87: 0 | AU87: 0 | AV87: 0 | AW87: 0 | AX87: 3700 | AY87: 0 | AZ87: 0 | BA87: 0
A88: One-time: Apple Studio Display 2026 | B88: 1290 | C88: 0 | D88: 0 | E88: 0 | F88: 0 | G88: 0 | H88: 0 | I88: 0 | J88: 0 | K88: 0 | L88: 0 | M88: 0 | N88: 0 | O88: 0 | P88: 0 | Q88: 0 | R88: 0 | S88: 0 | T88: 0 | U88: 0 | V88: 0 | W88: 0 | X88: 0 | Y88: 0 | Z88: 0 | AA88: 0 | AB88: 0 | AC88: 0 | AD88: 0 | AE88: 0 | AF88: 0 | AG88: 0 | AH88: 0 | AI88: 0 | AJ88: 0 | AK88: 0 | AL88: 0 | AM88: 0 | AN88: 0 | AO88: 0 | AP88: 0 | AQ88: 0 | AR88: 0 | AS88: 0 | AT88: 0 | AU88: 0 | AV88: 0 | AW88: 0 | AX88: 1290 | AY88: 0 | AZ88: 0 | BA88: 0
... A93: One-time: Domain .ai (2yr reg) | B93: 128 | C93: 0 | D93: 0 | E93: 0 | F93: 0 | G93: 0 | H93: 0 | I93: 0 | J93: 0 | K93: 0 | L93: 0 | M93: 0 | N93: 0 | O93: 0 | P93: 0 | Q93: 0 | R93: 0 | S93: 0 | T93: 0 | U93: 0 | V93: 0 | W93: 0 | X93: 0 | Y93: 0 | Z93: 0 | AA93: 0 | AB93: 0 | AC93: 0 | AD93: 0 | AE93: 0 | AF93: 0 | AG93: 0 | AH93: 0 | AI93: 0 | AJ93: 0 | AK93: 0 | AL93: 0 | AM93: 0 | AN93: 0 | AO93: 0 | AP93: 0 | AQ93: 0 | AR93: 0 | AS93: 0 | AT93: 0 | AU93: 0 | AV93: 0 | AW93: 0 | AX93: 128 | AY93: 0 | AZ93: 0 | BA93: 0
A94: TOTAL COSTS | B94: =B32+B33+B34+B35+B36+B37+B38+B39+B40+B42+B43+B44+B45+B47+B48+B49+B50+B51+B52+B53+B54+B55+B56+B57+B58+B59+B61+B62+B63+B64+B65+B66+B68+B69+B71+B72+B74+B75+B77+B78+B79+B80+B81+B82+B83+B84+B85+B86+B87+B88+B89+B90+B91+B92+B93 | C94: =C32+C33+C34+C35+C36+C37+C38+C39+C40+C42+C43+C44+C45+C47+C48+C49+C50+C51+C52+C53+C54+C55+C56+C57+C58+C59+C61+C62+C63+C64+C65+C66+C68+C69+C71+C72+C74+C75+C77+C78+C79+C80+C81+C82+C83+C84+C85+C86+C87+C88+C89+C90+C91+C92+C93 | D94: =D32+D33+D34+D35+D36+D37+D38+D39+D40+D42+D43+D44+D45+D47+D48+D49+D50+D51+D52+D53+D54+D55+D56+D57+D58+D59+D61+D62+D63+D64+D65+D66+D68+D69+D71+D72+D74+D75+D77+D78+D79+D80+D81+D82+D83+D84+D85+D86+D87+D88+D89+D90+D91+D92+D93 | E94: =E32+E33+E34+E35+E36+E37+E38+E39+E40+E42+E43+E44+E45+E47+E48+E49+E50+E51+E52+E53+E54+E55+E56+E57+E58+E59+E61+E62+E63+E64+E65+E66+E68+E69+E71+E72+E74+E75+E77+E78+E79+E80+E81+E82+E83+E84+E85+E86+E87+E88+E89+E90+E91+E92+E93 | F94: =F32+F33+F34+F35+F36+F37+F38+F39+F40+F42+F43+F44+F45+F47+F48+F49+F50+F51+F52+F53+F54+F55+F56+F57+F58+F59+F61+F62+F63+F64+F65+F66+F68+F69+F71+F72+F74+F75+F77+F78+F79+F80+F81+F82+F83+F84+F85+F86+F87+F88+F89+F90+F91+F92+F93 | G94: =G32+G33+G34+G35+G36+G37+G38+G39+G40+G42+G43+G44+G45+G47+G48+G49+G50+G51+G52+G53+G54+G55+G56+G57+G58+G59+G61+G62+G63+G64+G65+G66+G68+G69+G71+G72+G74+G75+G77+G78+G79+G80+G81+G82+G83+G84+G85+G86+G87+G88+G89+G90+G91+G92+G93 | H94: =H32+H33+H34+H35+H36+H37+H38+H39+H40+H42+H43+H44+H45+H47+H48+H49+H50+H51+H52+H53+H54+H55+H56+H57+H58+H59+H61+H62+H63+H64+H65+H66+H68+H69+H71+H72+H74+H75+H77+H78+H79+H80+H81+H82+H83+H84+H85+H86+H87+H88+H89+H90+H91+H92+H93 | I94: =I32+I33+I34+I35+I36+I37+I38+I39+I40+I42+I43+I44+I45+I47+I48+I49+I50+I51+I52+I53+I54+I55+I56+I57+I58+I59+I61+I62+I63+I64+I65+I66+I68+I69+I71+I72+I74+I75+I77+I78+I79+I80+I81+I82+I83+I84+I85+I86+I87+I88+I89+I90+I91+I92+I93 | ... BA94: =BA32+BA33+BA34+BA35+BA36+BA37+BA38+BA39+BA40+BA42+BA43+BA44+BA45+BA47+BA48+BA49+BA50+BA51+BA52+BA53+BA54+BA55+BA56+BA57+BA58+BA59+BA61+BA62+BA63+BA64+BA65+BA66+BA68+BA69+BA71+BA72+BA74+BA75+BA77+BA78+BA79+BA80+BA81+BA82+BA83+BA84+BA85+BA86+BA87+BA88+BA89+BA90+BA91+BA92+BA93
A96: PROFITABILITY
A97: EBITDA | B97: =B26-B94 | C97: =C26-C94 | D97: =D26-D94 | E97: =E26-E94 | F97: =F26-F94 | G97: =G26-G94 | H97: =H26-H94 | I97: =I26-I94 | ... BA97: =BA26-BA94
A98: EBITDA margin | B98: =IF(B26=0,0,B97/B26) | C98: =IF(C26=0,0,C97/C26) | D98: =IF(D26=0,0,D97/D26) | E98: =IF(E26=0,0,E97/E26) | F98: =IF(F26=0,0,F97/F26) | G98: =IF(G26=0,0,G97/G26) | H98: =IF(H26=0,0,H97/H26) | I98: =IF(I26=0,0,I97/I26) | ... AW98: =IF(AW26=0,0,AW97/AW26)
A99: Cumulative EBITDA | B99: =B97 | C99: =B99+C97 | D99: =C99+D97 | E99: =D99+E97 | F99: =E99+F97 | G99: =F99+G97 | H99: =G99+H97 | I99: =H99+I97 | J99: =I99+J97 | ... AW99: =AV99+AW97 | AX99: =M99 | AY99: =Y99 | AZ99: =AK99 | BA99: =AW99

Sheet Cash Flow
A1: LUMINA — CASH FLOW (CHF) — ZUG/BAAR
B3: Y1 | C3: Y1 | D3: Y1 | E3: Y1 | F3: Y1 | G3: Y1 | H3: Y1 | I3: Y1 | J3: Y1 | K3: Y1 | L3: Y1 | M3: Y1 | N3: Y2 | O3: Y2 | P3: Y2 | Q3: Y2 | R3: Y2 | S3: Y2 | T3: Y2 | U3: Y2 | V3: Y2 | W3: Y2 | X3: Y2 | Y3: Y2 | Z3: Y3 | AA3: Y3 | AB3: Y3 | AC3: Y3 | AD3: Y3 | AE3: Y3 | AF3: Y3 | AG3: Y3 | AH3: Y3 | AI3: Y3 | AJ3: Y3 | AK3: Y3 | AL3: Y4 | AM3: Y4 | AN3: Y4 | AO3: Y4 | AP3: Y4 | AQ3: Y4 | AR3: Y4 | AS3: Y4 | AT3: Y4 | AU3: Y4 | AV3: Y4 | AW3: Y4 | AX3: Y1 | AY3: Y2 | AZ3: Y3 | BA3: Y4
A4: Month | B4: M1 | C4: M2 | D4: M3 | E4: M4 | F4: M5 | G4: M6 | H4: M7 | I4: M8 | J4: M9 | K4: M10 | L4: M11 | M4: M12 | N4: M13 | O4: M14 | P4: M15 | Q4: M16 | R4: M17 | S4: M18 | T4: M19 | U4: M20 | V4: M21 | W4: M22 | X4: M23 | Y4: M24 | Z4: M25 | AA4: M26 | AB4: M27 | AC4: M28 | AD4: M29 | AE4: M30 | AF4: M31 | AG4: M32 | AH4: M33 | AI4: M34 | AJ4: M35 | AK4: M36 | AL4: M37 | AM4: M38 | AN4: M39 | AO4: M40 | AP4: M41 | AQ4: M42 | AR4: M43 | AS4: M44 | AT4: M45 | AU4: M46 | AV4: M47 | AW4: M48
A5: CASH INFLOWS
A6: Initial capital (CHF 200K) | B6: 200000 | C6: 0 | D6: 0 | E6: 0 | F6: 0 | G6: 0 | H6: 0 | I6: 0 | J6: 0 | K6: 0 | L6: 0 | M6: 0 | N6: 0 | O6: 0 | P6: 0 | Q6: 0 | R6: 0 | S6: 0 | T6: 0 | U6: 0 | V6: 0 | W6: 0 | X6: 0 | Y6: 0 | Z6: 0 | AA6: 0 | AB6: 0 | AC6: 0 | AD6: 0 | AE6: 0 | AF6: 0 | AG6: 0 | AH6: 0 | AI6: 0 | AJ6: 0 | AK6: 0 | AL6: 0 | AM6: 0 | AN6: 0 | AO6: 0 | AP6: 0 | AQ6: 0 | AR6: 0 | AS6: 0 | AT6: 0 | AU6: 0 | AV6: 0 | AW6: 0 | AX6: 200000 | AY6: 0 | AZ6: 0 | BA6: 0
A7: Revenue | B7: ='Monthly P&L'!B26 | C7: ='Monthly P&L'!C26 | D7: ='Monthly P&L'!D26 | E7: ='Monthly P&L'!E26 | F7: ='Monthly P&L'!F26 | G7: ='Monthly P&L'!G26 | H7: ='Monthly P&L'!H26 | I7: ='Monthly P&L'!I26 | ... BA7: ='Monthly P&L'!BA26
A8: TOTAL INFLOWS | B8: =B6+B7 | C8: =C6+C7 | D8: =D6+D7 | E8: =E6+E7 | F8: =F6+F7 | G8: =G6+G7 | H8: =H6+H7 | I8: =I6+I7 | ... BA8: =BA6+BA7
A10: CASH OUTFLOWS — EVERY ITEM
A11: — People
A12: CEO gross salary (CHF) | B12: ='Monthly P&L'!B32 | C12: ='Monthly P&L'!C32 | D12: ='Monthly P&L'!D32 | E12: ='Monthly P&L'!E32 | F12: ='Monthly P&L'!F32 | G12: ='Monthly P&L'!G32 | H12: ='Monthly P&L'!H32 | I12: ='Monthly P&L'!I32 | ... BA12: ='Monthly P&L'!BA32
A13: CEO employer social (10.1%) | B13: ='Monthly P&L'!B33 | C13: ='Monthly P&L'!C33 | D13: ='Monthly P&L'!D33 | E13: ='Monthly P&L'!E33 | F13: ='Monthly P&L'!F33 | G13: ='Monthly P&L'!G33 | H13: ='Monthly P&L'!H33 | I13: ='Monthly P&L'!I33 | ... BA13: ='Monthly P&L'!BA33
A14: Developer FT (€4K/mo) | B14: ='Monthly P&L'!B34 | C14: ='Monthly P&L'!C34 | D14: ='Monthly P&L'!D34 | E14: ='Monthly P&L'!E34 | F14: ='Monthly P&L'!F34 | G14: ='Monthly P&L'!G34 | H14: ='Monthly P&L'!H34 | I14: ='Monthly P&L'!I34 | ... BA14: ='Monthly P&L'!BA34
A15: PM PT (€4K/mo) | B15: ='Monthly P&L'!B35 | C15: ='Monthly P&L'!C35 | D15: ='Monthly P&L'!D35 | E15: ='Monthly P&L'!E35 | F15: ='Monthly P&L'!F35 | G15: ='Monthly P&L'!G35 | H15: ='Monthly P&L'!H35 | I15: ='Monthly P&L'!I35 | ... BA15: ='Monthly P&L'!BA35
A16: CS/Implementation (€5K/mo, M12+) | B16: ='Monthly P&L'!B36 | C16: ='Monthly P&L'!C36 | D16: ='Monthly P&L'!D36 | E16: ='Monthly P&L'!E36 | F16: ='Monthly P&L'!F36 | G16: ='Monthly P&L'!G36 | H16: ='Monthly P&L'!H36 | I16: ='Monthly P&L'!I36 | ... BA16: ='Monthly P&L'!BA36
A17: Senior Engineer (€7K/mo, M18+) | B17: ='Monthly P&L'!B37 | C17: ='Monthly P&L'!C37 | D17: ='Monthly P&L'!D37 | E17: ='Monthly P&L'!E37 | F17: ='Monthly P&L'!F37 | G17: ='Monthly P&L'!G37 | H17: ='Monthly P&L'!H37 | I17: ='Monthly P&L'!I37 | ... BA17: ='Monthly P&L'!BA37
A18: Sales/BD (€6K/mo, M18+) | B18: ='Monthly P&L'!B38 | C18: ='Monthly P&L'!C38 | D18: ='Monthly P&L'!D38 | E18: ='Monthly P&L'!E38 | F18: ='Monthly P&L'!F38 | G18: ='Monthly P&L'!G38 | H18: ='Monthly P&L'!H38 | I18: ='Monthly P&L'!I38 | ... BA18: ='Monthly P&L'!BA38
A19: Engineer (€6K/mo, M30+) | B19: ='Monthly P&L'!B39 | C19: ='Monthly P&L'!C39 | D19: ='Monthly P&L'!D39 | E19: ='Monthly P&L'!E39 | F19: ='Monthly P&L'!F39 | G19: ='Monthly P&L'!G39 | H19: ='Monthly P&L'!H39 | I19: ='Monthly P&L'!I39 | ... BA19: ='Monthly P&L'!BA39
A20: Marketing (€5K/mo, M36+) | B20: ='Monthly P&L'!B40 | C20: ='Monthly P&L'!C40 | D20: ='Monthly P&L'!D40 | E20: ='Monthly P&L'!E40 | F20: ='Monthly P&L'!F40 | G20: ='Monthly P&L'!G40 | H20: ='Monthly P&L'!H40 | I20: ='Monthly P&L'!I40 | ... BA20: ='Monthly P&L'!BA40
A21: — AI & Technology
A22: AI COGS (€50/hotel/mo) | B22: ='Monthly P&L'!B42 | C22: ='Monthly P&L'!C42 | D22: ='Monthly P&L'!D42 | E22: ='Monthly P&L'!E42 | F22: ='Monthly P&L'!F42 | G22: ='Monthly P&L'!G42 | H22: ='Monthly P&L'!H42 | I22: ='Monthly P&L'!I42 | ... BA22: ='Monthly P&L'!BA42
A23: Claude Code Max 20x ($200) | B23: ='Monthly P&L'!B43 | C23: ='Monthly P&L'!C43 | D23: ='Monthly P&L'!D43 | E23: ='Monthly P&L'!E43 | F23: ='Monthly P&L'!F43 | G23: ='Monthly P&L'!G43 | H23: ='Monthly P&L'!H43 | I23: ='Monthly P&L'!I43 | ... BA23: ='Monthly P&L'!BA43
A24: OpenAI Codex Pro ($200) | B24: ='Monthly P&L'!B44 | C24: ='Monthly P&L'!C44 | D24: ='Monthly P&L'!D44 | E24: ='Monthly P&L'!E44 | F24: ='Monthly P&L'!F44 | G24: ='Monthly P&L'!G44 | H24: ='Monthly P&L'!H44 | I24: ='Monthly P&L'!I44 | ... BA24: ='Monthly P&L'!BA44
A25: Perplexity Max ($200) | B25: ='Monthly P&L'!B45 | C25: ='Monthly P&L'!C45 | D25: ='Monthly P&L'!D45 | E25: ='Monthly P&L'!E45 | F25: ='Monthly P&L'!F45 | G25: ='Monthly P&L'!G45 | H25: ='Monthly P&L'!H45 | I25: ='Monthly P&L'!I45 | ... BA25: ='Monthly P&L'!BA45
A26: — Infrastructure (SaaS)
A27: Supabase Pro + compute | B27: ='Monthly P&L'!B47 | C27: ='Monthly P&L'!C47 | D27: ='Monthly P&L'!D47 | E27: ='Monthly P&L'!E47 | F27: ='Monthly P&L'!F47 | G27: ='Monthly P&L'!G47 | H27: ='Monthly P&L'!H47 | I27: ='Monthly P&L'!I47 | ... BA27: ='Monthly P&L'!BA47
A28: Vercel Pro | B28: ='Monthly P&L'!B48 | C28: ='Monthly P&L'!C48 | D28: ='Monthly P&L'!D48 | E28: ='Monthly P&L'!E48 | F28: ='Monthly P&L'!F48 | G28: ='Monthly P&L'!G48 | H28: ='Monthly P&L'!H48 | I28: ='Monthly P&L'!I48 | ... BA28: ='Monthly P&L'!BA48
A29: DataForSEO usage | B29: ='Monthly P&L'!B49 | C29: ='Monthly P&L'!C49 | D29: ='Monthly P&L'!D49 | E29: ='Monthly P&L'!E49 | F29: ='Monthly P&L'!F49 | G29: ='Monthly P&L'!G49 | H29: ='Monthly P&L'!H49 | I29: ='Monthly P&L'!I49 | ... BA29: ='Monthly P&L'!BA49
A30: SerpApi Developer | B30: ='Monthly P&L'!B50 | C30: ='Monthly P&L'!C50 | D30: ='Monthly P&L'!D50 | E30: ='Monthly P&L'!E50 | F30: ='Monthly P&L'!F50 | G30: ='Monthly P&L'!G50 | H30: ='Monthly P&L'!H50 | I30: ='Monthly P&L'!I50 | ... BA30: ='Monthly P&L'!BA50
A31: Firecrawl | B31: ='Monthly P&L'!B51 | C31: ='Monthly P&L'!C51 | D31: ='Monthly P&L'!D51 | E31: ='Monthly P&L'!E51 | F31: ='Monthly P&L'!F51 | G31: ='Monthly P&L'!G51 | H31: ='Monthly P&L'!H51 | I31: ='Monthly P&L'!I51 | ... BA31: ='Monthly P&L'!BA51
A32: Google Workspace | B32: ='Monthly P&L'!B52 | C32: ='Monthly P&L'!C52 | D32: ='Monthly P&L'!D52 | E32: ='Monthly P&L'!E52 | F32: ='Monthly P&L'!F52 | G32: ='Monthly P&L'!G52 | H32: ='Monthly P&L'!H52 | I32: ='Monthly P&L'!I52 | ... BA32: ='Monthly P&L'!BA52
A33: Domain .ai renewal | B33: ='Monthly P&L'!B53 | C33: ='Monthly P&L'!C53 | D33: ='Monthly P&L'!D53 | E33: ='Monthly P&L'!E53 | F33: ='Monthly P&L'!F53 | G33: ='Monthly P&L'!G53 | H33: ='Monthly P&L'!H53 | I33: ='Monthly P&L'!I53 | ... BA33: ='Monthly P&L'!BA53
A34: 1Password Business | B34: ='Monthly P&L'!B54 | C34: ='Monthly P&L'!C54 | D34: ='Monthly P&L'!D54 | E34: ='Monthly P&L'!E54 | F34: ='Monthly P&L'!F54 | G34: ='Monthly P&L'!G54 | H34: ='Monthly P&L'!H54 | I34: ='Monthly P&L'!I54 | ... BA34: ='Monthly P&L'!BA54
A35: Canva Pro | B35: ='Monthly P&L'!B55 | C35: ='Monthly P&L'!C55 | D35: ='Monthly P&L'!D55 | E35: ='Monthly P&L'!E55 | F35: ='Monthly P&L'!F55 | G35: ='Monthly P&L'!G55 | H35: ='Monthly P&L'!H55 | I35: ='Monthly P&L'!I55 | ... BA35: ='Monthly P&L'!BA55
A36: Sentry monitoring | B36: ='Monthly P&L'!B56 | C36: ='Monthly P&L'!C56 | D36: ='Monthly P&L'!D56 | E36: ='Monthly P&L'!E56 | F36: ='Monthly P&L'!F56 | G36: ='Monthly P&L'!G56 | H36: ='Monthly P&L'!H56 | I36: ='Monthly P&L'!I56 | ... BA36: ='Monthly P&L'!BA56
A37: Resend email | B37: ='Monthly P&L'!B57 | C37: ='Monthly P&L'!C57 | D37: ='Monthly P&L'!D57 | E37: ='Monthly P&L'!E57 | F37: ='Monthly P&L'!F57 | G37: ='Monthly P&L'!G57 | H37: ='Monthly P&L'!H57 | I37: ='Monthly P&L'!I57 | ... BA37: ='Monthly P&L'!BA57
A38: Notion | B38: ='Monthly P&L'!B58 | C38: ='Monthly P&L'!C58 | D38: ='Monthly P&L'!D58 | E38: ='Monthly P&L'!E58 | F38: ='Monthly P&L'!F58 | G38: ='Monthly P&L'!G58 | H38: ='Monthly P&L'!H58 | I38: ='Monthly P&L'!I58 | ... BA38: ='Monthly P&L'!BA58
A39: Cloudflare Pro | B39: ='Monthly P&L'!B59 | C39: ='Monthly P&L'!C59 | D39: ='Monthly P&L'!D59 | E39: ='Monthly P&L'!E59 | F39: ='Monthly P&L'!F59 | G39: ='Monthly P&L'!G59 | H39: ='Monthly P&L'!H59 | I39: ='Monthly P&L'!I59 | ... BA39: ='Monthly P&L'!BA59
A40: — Admin & Professional
A41: Slack Pro | B41: ='Monthly P&L'!B61 | C41: ='Monthly P&L'!C61 | D41: ='Monthly P&L'!D61 | E41: ='Monthly P&L'!E61 | F41: ='Monthly P&L'!F61 | G41: ='Monthly P&L'!G61 | H41: ='Monthly P&L'!H61 | I41: ='Monthly P&L'!I61 | ... BA41: ='Monthly P&L'!BA61
A42: GitHub Actions (CI/CD) | B42: ='Monthly P&L'!B62 | C42: ='Monthly P&L'!C62 | D42: ='Monthly P&L'!D62 | E42: ='Monthly P&L'!E62 | F42: ='Monthly P&L'!F62 | G42: ='Monthly P&L'!G62 | H42: ='Monthly P&L'!H62 | I42: ='Monthly P&L'!I62 | ... BA42: ='Monthly P&L'!BA62
A43: Upstash Redis (caching) | B43: ='Monthly P&L'!B63 | C43: ='Monthly P&L'!C63 | D43: ='Monthly P&L'!D63 | E43: ='Monthly P&L'!E63 | F43: ='Monthly P&L'!F63 | G43: ='Monthly P&L'!G63 | H43: ='Monthly P&L'!H63 | I43: ='Monthly P&L'!I63 | ... BA43: ='Monthly P&L'!BA63
A44: PostHog analytics | B44: ='Monthly P&L'!B64 | C44: ='Monthly P&L'!C64 | D44: ='Monthly P&L'!D64 | E44: ='Monthly P&L'!E64 | F44: ='Monthly P&L'!F64 | G44: ='Monthly P&L'!G64 | H44: ='Monthly P&L'!H64 | I44: ='Monthly P&L'!I64 | ... BA44: ='Monthly P&L'!BA64
A45: Misc SaaS + overages | B45: ='Monthly P&L'!B65 | C45: ='Monthly P&L'!C65 | D45: ='Monthly P&L'!D65 | E45: ='Monthly P&L'!E65 | F45: ='Monthly P&L'!F65 | G45: ='Monthly P&L'!G65 | H45: ='Monthly P&L'!H65 | I45: ='Monthly P&L'!I65 | ... BA45: ='Monthly P&L'!BA65
A46: Treuhand / accounting | B46: ='Monthly P&L'!B66 | C46: ='Monthly P&L'!C66 | D46: ='Monthly P&L'!D66 | E46: ='Monthly P&L'!E66 | F46: ='Monthly P&L'!F66 | G46: ='Monthly P&L'!G66 | H46: ='Monthly P&L'!H66 | I46: ='Monthly P&L'!I66 | ... BA46: ='Monthly P&L'!BA66
A47: — Workspace
A48: Legal retainer | B48: ='Monthly P&L'!B68 | C48: ='Monthly P&L'!C68 | D48: ='Monthly P&L'!D68 | E48: ='Monthly P&L'!E68 | F48: ='Monthly P&L'!F68 | G48: ='Monthly P&L'!G68 | H48: ='Monthly P&L'!H68 | I48: ='Monthly P&L'!I68 | ... BA48: ='Monthly P&L'!BA68
A49: D&O insurance (CHF 1M cover) | B49: ='Monthly P&L'!B69 | C49: ='Monthly P&L'!C69 | D49: ='Monthly P&L'!D69 | E49: ='Monthly P&L'!E69 | F49: ='Monthly P&L'!F69 | G49: ='Monthly P&L'!G69 | H49: ='Monthly P&L'!H69 | I49: ='Monthly P&L'!I69 | ... BA49: ='Monthly P&L'!BA69
A50: — Sales & Marketing
A51: Cyber insurance | B51: ='Monthly P&L'!B71 | C51: ='Monthly P&L'!C71 | D51: ='Monthly P&L'!D71 | E51: ='Monthly P&L'!E71 | F51: ='Monthly P&L'!F71 | G51: ='Monthly P&L'!G71 | H51: ='Monthly P&L'!H71 | I51: ='Monthly P&L'!I71 | ... BA51: ='Monthly P&L'!BA71
A52: General liability insurance | B52: ='Monthly P&L'!B72 | C52: ='Monthly P&L'!C72 | D52: ='Monthly P&L'!D72 | E52: ='Monthly P&L'!E72 | F52: ='Monthly P&L'!F72 | G52: ='Monthly P&L'!G72 | H52: ='Monthly P&L'!H72 | I52: ='Monthly P&L'!I72 | ... BA52: ='Monthly P&L'!BA72
A53: — Variable & Other
A54: Banking + FX (UBS/Wise) | B54: ='Monthly P&L'!B74 | C54: ='Monthly P&L'!C74 | D54: ='Monthly P&L'!D74 | E54: ='Monthly P&L'!E74 | F54: ='Monthly P&L'!F74 | G54: ='Monthly P&L'!G74 | H54: ='Monthly P&L'!H74 | I54: ='Monthly P&L'!I74 | ... BA54: ='Monthly P&L'!BA74
A55: Internet (Sunrise 1Gbit) | B55: ='Monthly P&L'!B75 | C55: ='Monthly P&L'!C75 | D55: ='Monthly P&L'!D75 | E55: ='Monthly P&L'!E75 | F55: ='Monthly P&L'!F75 | G55: ='Monthly P&L'!G75 | H55: ='Monthly P&L'!H75 | I55: ='Monthly P&L'!I75 | ... BA55: ='Monthly P&L'!BA75
A56: — One-Time (M1 only)
A57: Coworking (Westhive Zug) | B57: ='Monthly P&L'!B77 | C57: ='Monthly P&L'!C77 | D57: ='Monthly P&L'!D77 | E57: ='Monthly P&L'!E77 | F57: ='Monthly P&L'!F77 | G57: ='Monthly P&L'!G77 | H57: ='Monthly P&L'!H77 | I57: ='Monthly P&L'!I77 | ... BA57: ='Monthly P&L'!BA77
A58: Travel (client visits) | B58: ='Monthly P&L'!B78 | C58: ='Monthly P&L'!C78 | D58: ='Monthly P&L'!D78 | E58: ='Monthly P&L'!E78 | F58: ='Monthly P&L'!F78 | G58: ='Monthly P&L'!G78 | H58: ='Monthly P&L'!H78 | I58: ='Monthly P&L'!I78 | ... BA58: ='Monthly P&L'!BA78
A59: Marketing & events | B59: ='Monthly P&L'!B79 | C59: ='Monthly P&L'!C79 | D59: ='Monthly P&L'!D79 | E59: ='Monthly P&L'!E79 | F59: ='Monthly P&L'!F79 | G59: ='Monthly P&L'!G79 | H59: ='Monthly P&L'!H79 | I59: ='Monthly P&L'!I79 | ... BA59: ='Monthly P&L'!BA79
A60: Payment processing (Stripe 3%) | B60: ='Monthly P&L'!B80 | C60: ='Monthly P&L'!C80 | D60: ='Monthly P&L'!D80 | E60: ='Monthly P&L'!E80 | F60: ='Monthly P&L'!F80 | G60: ='Monthly P&L'!G80 | H60: ='Monthly P&L'!H80 | I60: ='Monthly P&L'!I80 | ... BA60: ='Monthly P&L'!BA80
A61: Contingency buffer | B61: ='Monthly P&L'!B81 | C61: ='Monthly P&L'!C81 | D61: ='Monthly P&L'!D81 | E61: ='Monthly P&L'!E81 | F61: ='Monthly P&L'!F81 | G61: ='Monthly P&L'!G81 | H61: ='Monthly P&L'!H81 | I61: ='Monthly P&L'!I81 | ... BA61: ='Monthly P&L'!BA81
A62: One-time: Nexova AG Plus formation | B62: ='Monthly P&L'!B82 | C62: ='Monthly P&L'!C82 | D62: ='Monthly P&L'!D82 | E62: ='Monthly P&L'!E82 | F62: ='Monthly P&L'!F82 | G62: ='Monthly P&L'!G82 | H62: ='Monthly P&L'!H82 | I62: ='Monthly P&L'!I82 | ... BA62: ='Monthly P&L'!BA82
A63: One-time: Commercial register entry | B63: ='Monthly P&L'!B83 | C63: ='Monthly P&L'!C83 | D63: ='Monthly P&L'!D83 | E63: ='Monthly P&L'!E83 | F63: ='Monthly P&L'!F83 | G63: ='Monthly P&L'!G83 | H63: ='Monthly P&L'!H83 | I63: ='Monthly P&L'!I83 | ... BA63: ='Monthly P&L'!BA83
A64: One-time: Notary fee (Zug tariff) | B64: ='Monthly P&L'!B84 | C64: ='Monthly P&L'!C84 | D64: ='Monthly P&L'!D84 | E64: ='Monthly P&L'!E84 | F64: ='Monthly P&L'!F84 | G64: ='Monthly P&L'!G84 | H64: ='Monthly P&L'!H84 | I64: ='Monthly P&L'!I84 | ... BA64: ='Monthly P&L'!BA84
A65: One-time: Capital deposit account | B65: ='Monthly P&L'!B85 | C65: ='Monthly P&L'!C85 | D65: ='Monthly P&L'!D85 | E65: ='Monthly P&L'!E85 | F65: ='Monthly P&L'!F85 | G65: ='Monthly P&L'!G85 | H65: ='Monthly P&L'!H85 | I65: ='Monthly P&L'!I85 | ... BA65: ='Monthly P&L'!BA85
A66: One-time: Signature certifications | B66: ='Monthly P&L'!B86 | C66: ='Monthly P&L'!C86 | D66: ='Monthly P&L'!D86 | E66: ='Monthly P&L'!E86 | F66: ='Monthly P&L'!F86 | G66: ='Monthly P&L'!G86 | H66: ='Monthly P&L'!H86 | I66: ='Monthly P&L'!I86 | ... BA66: ='Monthly P&L'!BA86
A67: One-time: MacBook Pro 16" M5 Pro 64GB/2TB | B67: ='Monthly P&L'!B87 | C67: ='Monthly P&L'!C87 | D67: ='Monthly P&L'!D87 | E67: ='Monthly P&L'!E87 | F67: ='Monthly P&L'!F87 | G67: ='Monthly P&L'!G87 | H67: ='Monthly P&L'!H87 | I67: ='Monthly P&L'!I87 | ... BA67: ='Monthly P&L'!BA87
A68: One-time: Apple Studio Display 2026 | B68: ='Monthly P&L'!B88 | C68: ='Monthly P&L'!C88 | D68: ='Monthly P&L'!D88 | E68: ='Monthly P&L'!E88 | F68: ='Monthly P&L'!F88 | G68: ='Monthly P&L'!G88 | H68: ='Monthly P&L'!H88 | I68: ='Monthly P&L'!I88 | ... BA68: ='Monthly P&L'!BA88
... A73: One-time: Domain .ai (2yr reg) | B73: ='Monthly P&L'!B93 | C73: ='Monthly P&L'!C93 | D73: ='Monthly P&L'!D93 | E73: ='Monthly P&L'!E93 | F73: ='Monthly P&L'!F93 | G73: ='Monthly P&L'!G93 | H73: ='Monthly P&L'!H93 | I73: ='Monthly P&L'!I93 | ... BA73: ='Monthly P&L'!BA93
A74: TOTAL OUTFLOWS | B74: =B12+B13+B14+B15+B16+B17+B18+B19+B20+B22+B23+B24+B25+B27+B28+B29+B30+B31+B32+B33+B34+B35+B36+B37+B38+B39+B41+B42+B43+B44+B45+B46+B48+B49+B51+B52+B54+B55+B57+B58+B59+B60+B61+B62+B63+B64+B65+B66+B67+B68+B69+B70+B71+B72+B73 | C74: =C12+C13+C14+C15+C16+C17+C18+C19+C20+C22+C23+C24+C25+C27+C28+C29+C30+C31+C32+C33+C34+C35+C36+C37+C38+C39+C41+C42+C43+C44+C45+C46+C48+C49+C51+C52+C54+C55+C57+C58+C59+C60+C61+C62+C63+C64+C65+C66+C67+C68+C69+C70+C71+C72+C73 | D74: =D12+D13+D14+D15+D16+D17+D18+D19+D20+D22+D23+D24+D25+D27+D28+D29+D30+D31+D32+D33+D34+D35+D36+D37+D38+D39+D41+D42+D43+D44+D45+D46+D48+D49+D51+D52+D54+D55+D57+D58+D59+D60+D61+D62+D63+D64+D65+D66+D67+D68+D69+D70+D71+D72+D73 | E74: =E12+E13+E14+E15+E16+E17+E18+E19+E20+E22+E23+E24+E25+E27+E28+E29+E30+E31+E32+E33+E34+E35+E36+E37+E38+E39+E41+E42+E43+E44+E45+E46+E48+E49+E51+E52+E54+E55+E57+E58+E59+E60+E61+E62+E63+E64+E65+E66+E67+E68+E69+E70+E71+E72+E73 | F74: =F12+F13+F14+F15+F16+F17+F18+F19+F20+F22+F23+F24+F25+F27+F28+F29+F30+F31+F32+F33+F34+F35+F36+F37+F38+F39+F41+F42+F43+F44+F45+F46+F48+F49+F51+F52+F54+F55+F57+F58+F59+F60+F61+F62+F63+F64+F65+F66+F67+F68+F69+F70+F71+F72+F73 | G74: =G12+G13+G14+G15+G16+G17+G18+G19+G20+G22+G23+G24+G25+G27+G28+G29+G30+G31+G32+G33+G34+G35+G36+G37+G38+G39+G41+G42+G43+G44+G45+G46+G48+G49+G51+G52+G54+G55+G57+G58+G59+G60+G61+G62+G63+G64+G65+G66+G67+G68+G69+G70+G71+G72+G73 | H74: =H12+H13+H14+H15+H16+H17+H18+H19+H20+H22+H23+H24+H25+H27+H28+H29+H30+H31+H32+H33+H34+H35+H36+H37+H38+H39+H41+H42+H43+H44+H45+H46+H48+H49+H51+H52+H54+H55+H57+H58+H59+H60+H61+H62+H63+H64+H65+H66+H67+H68+H69+H70+H71+H72+H73 | I74: =I12+I13+I14+I15+I16+I17+I18+I19+I20+I22+I23+I24+I25+I27+I28+I29+I30+I31+I32+I33+I34+I35+I36+I37+I38+I39+I41+I42+I43+I44+I45+I46+I48+I49+I51+I52+I54+I55+I57+I58+I59+I60+I61+I62+I63+I64+I65+I66+I67+I68+I69+I70+I71+I72+I73 | ... BA74: =BA12+BA13+BA14+BA15+BA16+BA17+BA18+BA19+BA20+BA22+BA23+BA24+BA25+BA27+BA28+BA29+BA30+BA31+BA32+BA33+BA34+BA35+BA36+BA37+BA38+BA39+BA41+BA42+BA43+BA44+BA45+BA46+BA48+BA49+BA51+BA52+BA54+BA55+BA57+BA58+BA59+BA60+BA61+BA62+BA63+BA64+BA65+BA66+BA67+BA68+BA69+BA70+BA71+BA72+BA73
A76: NET CASH FLOW
A77: Net cash flow | B77: =B8-B74 | C77: =C8-C74 | D77: =D8-D74 | E77: =E8-E74 | F77: =F8-F74 | G77: =G8-G74 | H77: =H8-H74 | I77: =I8-I74 | ... BA77: =BA8-BA74
A78: Closing cash balance | B78: =B77 | C78: =B78+C77 | D78: =C78+D77 | E78: =D78+E77 | F78: =E78+F77 | G78: =F78+G77 | H78: =G78+H77 | I78: =H78+I77 | J78: =I78+J77 | ... AW78: =AV78+AW77 | AX78: =M78 | AY78: =Y78 | AZ78: =AK78 | BA78: =AW78
A79: Net burn (costs - revenue) | B79: =B74-B7 | C79: =C74-C7 | D79: =D74-D7 | E79: =E74-E7 | F79: =F74-F7 | G79: =G74-G7 | H79: =H74-H7 | I79: =I74-I7 | ... AW79: =AW74-AW7
A80: Runway (months, net burn) | B80: =IF(B79<=0,999,B78/B79) | C80: =IF(C79<=0,999,C78/C79) | D80: =IF(D79<=0,999,D78/D79) | E80: =IF(E79<=0,999,E78/E79) | F80: =IF(F79<=0,999,F78/F79) | G80: =IF(G79<=0,999,G78/G79) | H80: =IF(H79<=0,999,H78/H79) | I80: =IF(I79<=0,999,I78/I79) | ... AW80: =IF(AW79<=0,999,AW78/AW79)
A81: 6-month runway clause met? | B81: YES | C81: =IF(B79<=0,"YES",IF(B78>=B79*6,"YES","NO")) | D81: =IF(C79<=0,"YES",IF(C78>=C79*6,"YES","NO")) | E81: =IF(D79<=0,"YES",IF(D78>=D79*6,"YES","NO")) | F81: =IF(E79<=0,"YES",IF(E78>=E79*6,"YES","NO")) | G81: =IF(F79<=0,"YES",IF(F78>=F79*6,"YES","NO")) | H81: =IF(G79<=0,"YES",IF(G78>=G79*6,"YES","NO")) | I81: =IF(H79<=0,"YES",IF(H78>=H79*6,"YES","NO")) | J81: =IF(I79<=0,"YES",IF(I78>=I79*6,"YES","NO")) | ... AW81: =IF(AV79<=0,"YES",IF(AV78>=AV79*6,"YES","NO"))
A82: (runway >= 6 OR profitable = always met)

Sheet Zug vs Zurich
A1: ZUG/BAAR vs ZURICH — FULL COMPARISON
A3: CORPORATE PROFIT TAX
B4: Baar/Zug | C4: Zurich City | D4: Annual Savings
A5: Effective rate | B5: 11.82% | C5: 19.59% | D5: -7.77pp
A6: Tax on CHF 100,000 profit | B6: 11820 | C6: 19590 | D6: 7770
A7: Tax on CHF 500,000 profit | B7: 59100 | C7: 97950 | D7: 38850
A8: Tax on CHF 1,000,000 profit | B8: 118200 | C8: 195900 | D8: 77700
A10: AFTER-TAX PROFIT BY YEAR
A11: Year | B11: EBITDA | C11: Tax (Zug) | D11: After-tax (Zug) | E11: Tax (Zurich) | F11: After-tax (ZH) | G11: Zug saves
A12: Y1 | B12: -133825 | C12: 0 | D12: -133825 | E12: 0 | F12: -133825 | G12: 0
A13: Y2 | B13: 415163 | C13: 49072 | D13: 366091 | E13: 81330 | F13: 333833 | G13: 32258
A14: Y3 | B14: 2097396 | C14: 247912 | D14: 1849484 | E14: 410880 | F14: 1686516 | G14: 162968
A15: Y4 | B15: 4814350 | C15: 569056 | D15: 4245294 | E15: 943131 | F15: 3871219 | G15: 374075
A16: CUMULATIVE TAX SAVINGS (ZUG) | G16: 569301
A18: OTHER DIFFERENCES
A19: Incorporation notary fee | B19: CHF 1,000 | C19: CHF 1,500 | D19: CHF 500 more
A20: FAK employer rate | B20: 1.35% | C20: 0.98% | D20: ~CHF 400/yr cheaper in ZH per employee
A21: Capital tax rate | B21: 0.07% | C21: 0.17% | D21: CHF 200 more/yr at CHF 200K equity
A22: Treuhand costs | B22: Similar | C22: Similar | D22: 10-20% higher in ZH on average
A23: Domiciliation | B23: CHF 29/mo basic | C23: CHF 50/mo basic | D23: Minimal difference
A24: Insurance | B24: Same | C24: Same | D24: Not canton-dependent
A26: VERDICT: Zug/Baar saves CHF 38K-78K/year in corporate tax alone.
A27: Incorporation cost difference is negligible. Choose Zug.

Sheet Valuation & Exit
A1: LUMINA — VALUATION & EXIT
A3: ARR MILESTONES
B4: ARR CHF | C4: ARR EUR | D4: Paying | E4: EBITDA/mo | F4: Cash
A5: M12 | B5: 498096 | C5: 540000 | D5: 45 | E5: 9376 | F5: 66175
A6: M24 | B6: 2085372 | C6: 2260811 | D6: 132 | E6: 116390 | F6: 481338
A7: M36 | B7: 3662676 | C7: 3970811 | D7: 232 | E7: 223735 | F7: 2578734
A8: M48 | B8: 6822804 | C8: 7396795 | D8: 333 | E8: 472258 | F8: 7393084
A10: VALUATION MATRIX (CHF)
B11: 6x | C11: 8x | D11: 10x | E11: 12x
A12: M12 | B12: 2988576 | C12: 3984768 | D12: 4980960 | E12: 5977152
A13: M24 | B13: 12512232 | C13: 16682976 | D13: 20853720 | E13: 25024464
A14: M36 | B14: 21976056 | C14: 29301408 | D14: 36626760 | E14: 43952112
A15: M48 | B15: 40936824 | C15: 54582432 | D15: 68228040 | E15: 81873648
A17: MARCO'S EQUITY VALUE (10x exit)
A18: M12: 20% kicker | B18: 996192 | C18: on CHF 4,980,960 valuation
A19: M24: 20% kicker | B19: 4170744 | C19: on CHF 20,853,720 valuation
A20: M36: 23% kicker | B20: 8424155 | C20: on CHF 36,626,760 valuation
A21: M48: 25% kicker | B21: 17057010 | C21: on CHF 68,228,040 valuation

Sheet Sensitivity
A1: LUMINA — SENSITIVITY & RUNWAY
A3: BREAKEVEN
A4: First EBITDA-positive | B4: M12
A5: Lowest cash | B5: 56799 | C5: M11
A6: Max drawdown | B6: 143201
A8: CEO STEP-UP TIMELINE
A9: M1: CHF 106,080/yr → CHF 9,737/mo
A10: M12: CHF 150,000/yr → CHF 13,689/mo
A11: M23: CHF 185,000/yr → CHF 16,817/mo
A12: M29: CHF 220,000/yr → CHF 19,945/mo
A14: VESTING STATUS
A15: M12: +5% if 15+ paying | B15: MET | C15: Cumul 25%
A16: M24: +7% if ARR≥€500K | B16: MET | C16: Cumul 32%
A17: M36: +8% if ARR≥€1.5M | B17: MET | C17: Cumul 40%
